{"source_update": "2026/07/08 16:29 UPDATE", "date": "2026-07-08", "lines": {"北海道・本州間電力連系設備": [{"time": "00:30", "flow": 233.8, "fwd_capacity": 700.0, "rev_capacity": 900.0, "fwd_free": 356.21, "rev_free": 523.8, "fwd_split": "495.225", "rev_split": "分断なし"}, {"time": "01:00", "flow": 263.3, "fwd_capacity": 700.0, "rev_capacity": 900.0, "fwd_free": 336.7, "rev_free": 548.19, "fwd_split": "485.336", "rev_split": "分断なし"}, {"time": "01:30", "flow": 240.9, "fwd_capacity": 700.0, "rev_capacity": 900.0, "fwd_free": 349.1, "rev_free": 524.28, "fwd_split": "474.984", "rev_split": "分断なし"}, {"time": "02:00", "flow": 139.8, "fwd_capacity": 700.0, "rev_capacity": 900.0, "fwd_free": 450.2, "rev_free": 423.658, "fwd_split": "359.552", "rev_split": "分断なし"}, {"time": "02:30", "flow": -2.5, "fwd_capacity": 700.0, "rev_capacity": 900.0, "fwd_free": 595.5, "rev_free": 297.5, "fwd_split": "196.362", "rev_split": "分断なし"}, {"time": "03:00", "flow": -37.1, "fwd_capacity": 700.0, "rev_capacity": 900.0, "fwd_free": 634.1, "rev_free": 262.9, "fwd_split": "113.748", "rev_split": "分断なし"}, {"time": "03:30", "flow": -85.1, "fwd_capacity": 700.0, "rev_capacity": 900.0, "fwd_free": 703.1, "rev_free": 214.9, "fwd_split": "84.65", "rev_split": "分断なし"}, {"time": "04:00", "flow": -102.1, "fwd_capacity": 700.0, "rev_capacity": 900.0, "fwd_free": 722.1, "rev_free": 194.9, "fwd_split": "70.876", "rev_split": "分断なし"}, {"time": "04:30", "flow": -85.8, "fwd_capacity": 700.0, "rev_capacity": 900.0, "fwd_free": 715.8, "rev_free": 169.2, "fwd_split": "80.552", "rev_split": "分断なし"}, {"time": "05:00", "flow": -17.8, "fwd_capacity": 700.0, "rev_capacity": 900.0, "fwd_free": 647.8, "rev_free": 237.2, "fwd_split": "159", "rev_split": "分断なし"}, {"time": "05:30", "flow": 43.4, "fwd_capacity": 700.0, "rev_capacity": 900.0, "fwd_free": 576.6, "rev_free": 298.4, "fwd_split": "124.853", "rev_split": "分断なし"}, {"time": "06:00", "flow": 141.9, "fwd_capacity": 700.0, "rev_capacity": 900.0, "fwd_free": 478.1, "rev_free": 396.9, "fwd_split": "222.545", "rev_split": "分断なし"}, {"time": "06:30", "flow": 173.0, "fwd_capacity": 700.0, "rev_capacity": 900.0, "fwd_free": 447.0, "rev_free": 422.0, "fwd_split": "186.45", "rev_split": "分断なし"}, {"time": "07:00", "flow": 96.9, "fwd_capacity": 700.0, "rev_capacity": 900.0, "fwd_free": 523.1, "rev_free": 344.9, "fwd_split": "114.018", "rev_split": "分断なし"}, {"time": "07:30", "flow": 26.3, "fwd_capacity": 700.0, "rev_capacity": 900.0, "fwd_free": 613.7, "rev_free": 273.3, "fwd_split": "71.848", "rev_split": "分断なし"}, {"time": "08:00", "flow": -50.9, "fwd_capacity": 700.0, "rev_capacity": 900.0, "fwd_free": 690.9, "rev_free": 195.1, "fwd_split": "59.279", "rev_split": "分断なし"}, {"time": "08:30", "flow": -86.6, "fwd_capacity": 700.0, "rev_capacity": 900.0, "fwd_free": 756.6, "rev_free": 177.4, "fwd_split": "278.836", "rev_split": "分断なし"}, {"time": "09:00", "flow": -163.5, "fwd_capacity": 700.0, "rev_capacity": 900.0, "fwd_free": 833.5, "rev_free": 169.689, "fwd_split": "246.381", "rev_split": "分断なし"}, {"time": "09:30", "flow": -66.5, "fwd_capacity": 700.0, "rev_capacity": 900.0, "fwd_free": 756.5, "rev_free": 185.5, "fwd_split": "264.442", "rev_split": "分断なし"}, {"time": "10:00", "flow": -88.7, "fwd_capacity": 700.0, "rev_capacity": 900.0, "fwd_free": 778.7, "rev_free": 163.3, "fwd_split": "191.062", "rev_split": "分断なし"}, {"time": "10:30", "flow": -50.5, "fwd_capacity": 700.0, "rev_capacity": 900.0, "fwd_free": 730.5, "rev_free": 311.35, "fwd_split": "334.462", "rev_split": "分断なし"}, {"time": "11:00", "flow": -142.2, "fwd_capacity": 700.0, "rev_capacity": 900.0, "fwd_free": 819.2, "rev_free": 180.8, "fwd_split": "256.823", "rev_split": "分断なし"}, {"time": "11:30", "flow": -230.2, "fwd_capacity": 700.0, "rev_capacity": 900.0, "fwd_free": 895.2, "rev_free": 139.8, "fwd_split": "182.41", "rev_split": "分断なし"}, {"time": "12:00", "flow": -174.4, "fwd_capacity": 700.0, "rev_capacity": 900.0, "fwd_free": 845.4, "rev_free": 164.6, "fwd_split": "76.974", "rev_split": "分断なし"}, {"time": "12:30", "flow": -226.3, "fwd_capacity": 700.0, "rev_capacity": 900.0, "fwd_free": 916.3, "rev_free": 105.632, "fwd_split": "0", "rev_split": "分断なし"}, {"time": "13:00", "flow": -83.2, "fwd_capacity": 700.0, "rev_capacity": 900.0, "fwd_free": 773.2, "rev_free": 201.8, "fwd_split": "0", "rev_split": "分断なし"}, {"time": "13:30", "flow": -37.5, "fwd_capacity": 700.0, "rev_capacity": 900.0, "fwd_free": 737.5, "rev_free": 177.5, "fwd_split": "170.212", "rev_split": "分断なし"}, {"time": "14:00", "flow": -41.1, "fwd_capacity": 700.0, "rev_capacity": 900.0, "fwd_free": 741.1, "rev_free": 180.9, "fwd_split": "138.371", "rev_split": "分断なし"}, {"time": "14:30", "flow": 78.2, "fwd_capacity": 700.0, "rev_capacity": 900.0, "fwd_free": 611.8, "rev_free": 306.2, "fwd_split": "234.702", "rev_split": "分断なし"}, {"time": "15:00", "flow": 250.3, "fwd_capacity": 700.0, "rev_capacity": 900.0, "fwd_free": 439.7, "rev_free": 485.3, "fwd_split": "306.269", "rev_split": "分断なし"}, {"time": "15:30", "flow": 148.1, "fwd_capacity": 700.0, "rev_capacity": 900.0, "fwd_free": 541.9, "rev_free": 368.97, "fwd_split": "314.409", "rev_split": "分断なし"}, {"time": "16:00", "flow": 372.4, "fwd_capacity": 700.0, "rev_capacity": 900.0, "fwd_free": 317.6, "rev_free": 607.4, "fwd_split": "636.817", "rev_split": "分断なし"}, {"time": "16:30", "flow": 319.9, "fwd_capacity": 700.0, "rev_capacity": 900.0, "fwd_free": 380.1, "rev_free": 563.9, "fwd_split": "423.055", "rev_split": "分断なし"}, {"time": "17:00", "flow": 276.2, "fwd_capacity": 700.0, "rev_capacity": 900.0, "fwd_free": 423.8, "rev_free": 538.2, "fwd_split": "378.446", "rev_split": "分断なし"}, {"time": "17:30", "flow": 290.9, "fwd_capacity": 700.0, "rev_capacity": 900.0, "fwd_free": 399.1, "rev_free": 565.9, "fwd_split": "372.022", "rev_split": "分断なし"}, {"time": "18:00", "flow": 278.2, "fwd_capacity": 700.0, "rev_capacity": 900.0, "fwd_free": 411.8, "rev_free": 561.2, "fwd_split": "410.169", "rev_split": "分断なし"}, {"time": "18:30", "flow": 318.2, "fwd_capacity": 700.0, "rev_capacity": 900.0, "fwd_free": 361.8, "rev_free": 602.2, "fwd_split": "457.753", "rev_split": "分断なし"}, {"time": "19:00", "flow": 280.0, "fwd_capacity": 700.0, "rev_capacity": 900.0, "fwd_free": 400.0, "rev_free": 565.0, "fwd_split": "410.258", "rev_split": "分断なし"}, {"time": "19:30", "flow": 201.6, "fwd_capacity": 700.0, "rev_capacity": 900.0, "fwd_free": 488.4, "rev_free": 486.6, "fwd_split": "310.085", "rev_split": "分断なし"}, {"time": "20:00", "flow": 122.8, "fwd_capacity": 700.0, "rev_capacity": 900.0, "fwd_free": 567.2, "rev_free": 407.8, "fwd_split": "200.024", "rev_split": "分断なし"}, {"time": "20:30", "flow": 137.1, "fwd_capacity": 700.0, "rev_capacity": 900.0, "fwd_free": 522.9, "rev_free": 412.1, "fwd_split": "159.539", "rev_split": "分断なし"}, {"time": "21:00", "flow": 170.1, "fwd_capacity": 700.0, "rev_capacity": 900.0, "fwd_free": 489.9, "rev_free": 445.1, "fwd_split": "186.377", "rev_split": "分断なし"}, {"time": "21:30", "flow": 161.6, "fwd_capacity": 700.0, "rev_capacity": 900.0, "fwd_free": 488.4, "rev_free": 426.6, "fwd_split": "144.162", "rev_split": "分断なし"}, {"time": "22:00", "flow": 249.1, "fwd_capacity": 700.0, "rev_capacity": 900.0, "fwd_free": 400.9, "rev_free": 514.1, "fwd_split": "182.451", "rev_split": "分断なし"}, {"time": "22:30", "flow": 187.2, "fwd_capacity": 700.0, "rev_capacity": 900.0, "fwd_free": 442.8, "rev_free": 442.2, "fwd_split": "105.865", "rev_split": "分断なし"}, {"time": "23:00", "flow": 370.8, "fwd_capacity": 700.0, "rev_capacity": 900.0, "fwd_free": 259.2, "rev_free": 625.8, "fwd_split": "202.664", "rev_split": "分断なし"}, {"time": "23:30", "flow": 416.9, "fwd_capacity": 700.0, "rev_capacity": 900.0, "fwd_free": 203.1, "rev_free": 671.9, "fwd_split": "173.417", "rev_split": "分断なし"}, {"time": "24:00", "flow": 481.8, "fwd_capacity": 700.0, "rev_capacity": 900.0, "fwd_free": 138.2, "rev_free": 736.8, "fwd_split": "165.147", "rev_split": "分断なし"}], "相馬双葉幹線": [{"time": "00:30", "flow": 2241.8, "fwd_capacity": 3110.0, "rev_capacity": 2360.0, "fwd_free": 868.2, "rev_free": 4522.59, "fwd_split": "5426.442", "rev_split": "分断なし"}, {"time": "01:00", "flow": 2371.4, "fwd_capacity": 3110.0, "rev_capacity": 2360.0, "fwd_free": 738.6, "rev_free": 4688.207, "fwd_split": "5470", "rev_split": "分断あり"}, {"time": "01:30", "flow": 2380.5, "fwd_capacity": 3110.0, "rev_capacity": 2360.0, "fwd_free": 729.5, "rev_free": 4662.588, "fwd_split": "5362.21", "rev_split": "分断なし"}, {"time": "02:00", "flow": 2305.0, "fwd_capacity": 3110.0, "rev_capacity": 2360.0, "fwd_free": 805.0, "rev_free": 4588.008, "fwd_split": "5201.602", "rev_split": "分断なし"}, {"time": "02:30", "flow": 2249.8, "fwd_capacity": 3110.0, "rev_capacity": 2360.0, "fwd_free": 860.2, "rev_free": 4532.808, "fwd_split": "5010.247", "rev_split": "分断なし"}, {"time": "03:00", "flow": 2191.2, "fwd_capacity": 3110.0, "rev_capacity": 2360.0, "fwd_free": 918.8, "rev_free": 4473.288, "fwd_split": "4912.286", "rev_split": "分断なし"}, {"time": "03:30", "flow": 2111.2, "fwd_capacity": 3110.0, "rev_capacity": 2360.0, "fwd_free": 998.8, "rev_free": 4421.958, "fwd_split": "4901.063", "rev_split": "分断なし"}, {"time": "04:00", "flow": 2042.3, "fwd_capacity": 3110.0, "rev_capacity": 2360.0, "fwd_free": 1067.7, "rev_free": 4402.3, "fwd_split": "4990.711", "rev_split": "分断なし"}, {"time": "04:30", "flow": 1981.9, "fwd_capacity": 3110.0, "rev_capacity": 2360.0, "fwd_free": 1128.1, "rev_free": 4216.328, "fwd_split": "4888.741", "rev_split": "分断なし"}, {"time": "05:00", "flow": 1777.8, "fwd_capacity": 3110.0, "rev_capacity": 2360.0, "fwd_free": 1332.2, "rev_free": 3970.103, "fwd_split": "4794.704", "rev_split": "分断なし"}, {"time": "05:30", "flow": 2246.9, "fwd_capacity": 3110.0, "rev_capacity": 2360.0, "fwd_free": 863.1, "rev_free": 4458.296, "fwd_split": "5229.019", "rev_split": "分断なし"}, {"time": "06:00", "flow": 2822.8, "fwd_capacity": 3110.0, "rev_capacity": 2360.0, "fwd_free": 287.2, "rev_free": 5022.913, "fwd_split": "5363.765", "rev_split": "分断なし"}, {"time": "06:30", "flow": 3069.7, "fwd_capacity": 3110.0, "rev_capacity": 2360.0, "fwd_free": 40.3, "rev_free": 5219.813, "fwd_split": "5470", "rev_split": "分断あり"}, {"time": "07:00", "flow": 3094.4, "fwd_capacity": 3110.0, "rev_capacity": 2360.0, "fwd_free": 15.6, "rev_free": 5236.557, "fwd_split": "5470", "rev_split": "分断あり"}, {"time": "07:30", "flow": 3109.8, "fwd_capacity": 3110.0, "rev_capacity": 2360.0, "fwd_free": 0.2, "rev_free": 5259.957, "fwd_split": "5470", "rev_split": "分断あり"}, {"time": "08:00", "flow": 3110.0, "fwd_capacity": 3110.0, "rev_capacity": 2360.0, "fwd_free": 0.0, "rev_free": 5250.157, "fwd_split": "5470", "rev_split": "分断あり"}, {"time": "08:30", "flow": 3610.0, "fwd_capacity": 3610.0, "rev_capacity": 2360.0, "fwd_free": 0.0, "rev_free": 5737.876, "fwd_split": "5970", "rev_split": "分断あり"}, {"time": "09:00", "flow": 3610.0, "fwd_capacity": 3610.0, "rev_capacity": 2360.0, "fwd_free": 0.0, "rev_free": 5776.741, "fwd_split": "5970", "rev_split": "分断あり"}, {"time": "09:30", "flow": 3610.0, "fwd_capacity": 3610.0, "rev_capacity": 2360.0, "fwd_free": 0.0, "rev_free": 5676.67, "fwd_split": "5970", "rev_split": "分断あり"}, {"time": "10:00", "flow": 3610.0, "fwd_capacity": 3610.0, "rev_capacity": 2360.0, "fwd_free": 0.0, "rev_free": 5654.907, "fwd_split": "5970", "rev_split": "分断あり"}, {"time": "10:30", "flow": 3610.0, "fwd_capacity": 3610.0, "rev_capacity": 2360.0, "fwd_free": 0.0, "rev_free": 5746.757, "fwd_split": "5970", "rev_split": "分断あり"}, {"time": "11:00", "flow": 3610.0, "fwd_capacity": 3610.0, "rev_capacity": 2360.0, "fwd_free": 0.0, "rev_free": 5795.554, "fwd_split": "5970", "rev_split": "分断あり"}, {"time": "11:30", "flow": 3610.0, "fwd_capacity": 3610.0, "rev_capacity": 2360.0, "fwd_free": 0.0, "rev_free": 5765.983, "fwd_split": "5970", "rev_split": "分断あり"}, {"time": "12:00", "flow": 3610.0, "fwd_capacity": 3610.0, "rev_capacity": 2360.0, "fwd_free": 0.0, "rev_free": 5731.503, "fwd_split": "5970", "rev_split": "分断あり"}, {"time": "12:30", "flow": 3610.0, "fwd_capacity": 3610.0, "rev_capacity": 2360.0, "fwd_free": 0.0, "rev_free": 5673.695, "fwd_split": "5970", "rev_split": "分断あり"}, {"time": "13:00", "flow": 3610.0, "fwd_capacity": 3610.0, "rev_capacity": 2360.0, "fwd_free": 0.0, "rev_free": 5610.352, "fwd_split": "5970", "rev_split": "分断あり"}, {"time": "13:30", "flow": 3660.0, "fwd_capacity": 3660.0, "rev_capacity": 2360.0, "fwd_free": 0.0, "rev_free": 5558.52, "fwd_split": "5892.087", "rev_split": "分断なし"}, {"time": "14:00", "flow": 3660.0, "fwd_capacity": 3660.0, "rev_capacity": 2360.0, "fwd_free": 0.0, "rev_free": 5573.17, "fwd_split": "5645.874", "rev_split": "分断なし"}, {"time": "14:30", "flow": 3660.0, "fwd_capacity": 3660.0, "rev_capacity": 2360.0, "fwd_free": 0.0, "rev_free": 5649.0, "fwd_split": "5687.465", "rev_split": "分断なし"}, {"time": "15:00", "flow": 3660.0, "fwd_capacity": 3660.0, "rev_capacity": 2360.0, "fwd_free": 0.0, "rev_free": 5641.506, "fwd_split": "5495.68", "rev_split": "分断なし"}, {"time": "15:30", "flow": 3660.0, "fwd_capacity": 3660.0, "rev_capacity": 2360.0, "fwd_free": 0.0, "rev_free": 5503.87, "fwd_split": "5435.231", "rev_split": "分断なし"}, {"time": "16:00", "flow": 3647.5, "fwd_capacity": 3660.0, "rev_capacity": 2360.0, "fwd_free": 12.5, "rev_free": 5505.5, "fwd_split": "5271.242", "rev_split": "分断なし"}, {"time": "16:30", "flow": 2735.9, "fwd_capacity": 3660.0, "rev_capacity": 2360.0, "fwd_free": 924.1, "rev_free": 4606.9, "fwd_split": "5034.199", "rev_split": "分断なし"}, {"time": "17:00", "flow": 2336.2, "fwd_capacity": 3710.0, "rev_capacity": 2360.0, "fwd_free": 1373.8, "rev_free": 4231.2, "fwd_split": "4661.682", "rev_split": "分断なし"}, {"time": "17:30", "flow": 2254.6, "fwd_capacity": 3710.0, "rev_capacity": 2360.0, "fwd_free": 1455.4, "rev_free": 4236.6, "fwd_split": "4529.54", "rev_split": "分断なし"}, {"time": "18:00", "flow": 1765.4, "fwd_capacity": 3710.0, "rev_capacity": 2360.0, "fwd_free": 1944.6, "rev_free": 3758.4, "fwd_split": "4389.495", "rev_split": "分断なし"}, {"time": "18:30", "flow": 1914.1, "fwd_capacity": 3710.0, "rev_capacity": 2360.0, "fwd_free": 1795.9, "rev_free": 4028.1, "fwd_split": "4305.906", "rev_split": "分断なし"}, {"time": "19:00", "flow": 1910.2, "fwd_capacity": 3710.0, "rev_capacity": 2360.0, "fwd_free": 1799.8, "rev_free": 3955.2, "fwd_split": "4079.606", "rev_split": "分断なし"}, {"time": "19:30", "flow": 1879.1, "fwd_capacity": 3710.0, "rev_capacity": 2360.0, "fwd_free": 1830.9, "rev_free": 3924.1, "fwd_split": "4227.791", "rev_split": "分断なし"}, {"time": "20:00", "flow": 1795.0, "fwd_capacity": 3710.0, "rev_capacity": 2360.0, "fwd_free": 1915.0, "rev_free": 3841.0, "fwd_split": "4187.29", "rev_split": "分断なし"}, {"time": "20:30", "flow": 1737.3, "fwd_capacity": 3710.0, "rev_capacity": 2360.0, "fwd_free": 1972.7, "rev_free": 3803.3, "fwd_split": "4032.317", "rev_split": "分断なし"}, {"time": "21:00", "flow": 1533.0, "fwd_capacity": 3710.0, "rev_capacity": 2360.0, "fwd_free": 2177.0, "rev_free": 3603.0, "fwd_split": "3782.402", "rev_split": "分断なし"}, {"time": "21:30", "flow": 1686.6, "fwd_capacity": 3710.0, "rev_capacity": 2360.0, "fwd_free": 2023.4, "rev_free": 3951.6, "fwd_split": "4003.096", "rev_split": "分断なし"}, {"time": "22:00", "flow": 1992.9, "fwd_capacity": 3710.0, "rev_capacity": 2360.0, "fwd_free": 1717.1, "rev_free": 4257.9, "fwd_split": "4083.414", "rev_split": "分断なし"}, {"time": "22:30", "flow": 2035.8, "fwd_capacity": 3210.0, "rev_capacity": 2360.0, "fwd_free": 1174.2, "rev_free": 4301.8, "fwd_split": "4092.125", "rev_split": "分断なし"}, {"time": "23:00", "flow": 2116.4, "fwd_capacity": 3210.0, "rev_capacity": 2360.0, "fwd_free": 1093.6, "rev_free": 4382.4, "fwd_split": "4108.012", "rev_split": "分断なし"}, {"time": "23:30", "flow": 2211.9, "fwd_capacity": 3210.0, "rev_capacity": 2360.0, "fwd_free": 998.1, "rev_free": 4481.9, "fwd_split": "4160.001", "rev_split": "分断なし"}, {"time": "24:00", "flow": 2377.5, "fwd_capacity": 3210.0, "rev_capacity": 2360.0, "fwd_free": 832.5, "rev_free": 4654.5, "fwd_split": "4178.536", "rev_split": "分断なし"}], "周波数変換設備": [{"time": "00:30", "flow": -482.3, "fwd_capacity": 1800.0, "rev_capacity": 1800.0, "fwd_free": 1682.3, "rev_free": 717.7, "fwd_split": "1697.235", "rev_split": "分断なし"}, {"time": "01:00", "flow": -288.0, "fwd_capacity": 1800.0, "rev_capacity": 1800.0, "fwd_free": 1488.0, "rev_free": 912.0, "fwd_split": "2400", "rev_split": "分断あり"}, {"time": "01:30", "flow": -428.7, "fwd_capacity": 1800.0, "rev_capacity": 1800.0, "fwd_free": 1628.7, "rev_free": 771.3, "fwd_split": "2400", "rev_split": "分断あり"}, {"time": "02:00", "flow": -655.1, "fwd_capacity": 1800.0, "rev_capacity": 1800.0, "fwd_free": 1855.1, "rev_free": 544.9, "fwd_split": "2310.758", "rev_split": "分断なし"}, {"time": "02:30", "flow": -697.7, "fwd_capacity": 1800.0, "rev_capacity": 1800.0, "fwd_free": 1897.7, "rev_free": 502.3, "fwd_split": "2291.377", "rev_split": "分断なし"}, {"time": "03:00", "flow": -620.3, "fwd_capacity": 1800.0, "rev_capacity": 1800.0, "fwd_free": 1820.3, "rev_free": 579.7, "fwd_split": "2332.644", "rev_split": "分断なし"}, {"time": "03:30", "flow": -540.7, "fwd_capacity": 1800.0, "rev_capacity": 1800.0, "fwd_free": 1740.7, "rev_free": 659.3, "fwd_split": "2400", "rev_split": "分断あり"}, {"time": "04:00", "flow": -465.0, "fwd_capacity": 1800.0, "rev_capacity": 1800.0, "fwd_free": 1665.0, "rev_free": 735.0, "fwd_split": "2291.548", "rev_split": "分断なし"}, {"time": "04:30", "flow": -497.5, "fwd_capacity": 1800.0, "rev_capacity": 1800.0, "fwd_free": 1613.88, "rev_free": 702.5, "fwd_split": "2194.57", "rev_split": "分断なし"}, {"time": "05:00", "flow": -551.5, "fwd_capacity": 1800.0, "rev_capacity": 1800.0, "fwd_free": 1609.904, "rev_free": 648.5, "fwd_split": "2035.168", "rev_split": "分断なし"}, {"time": "05:30", "flow": -397.8, "fwd_capacity": 1800.0, "rev_capacity": 1800.0, "fwd_free": 1597.8, "rev_free": 802.2, "fwd_split": "2400", "rev_split": "分断あり"}, {"time": "06:00", "flow": -745.1, "fwd_capacity": 1800.0, "rev_capacity": 1800.0, "fwd_free": 1788.504, "rev_free": 454.9, "fwd_split": "2243.404", "rev_split": "分断あり"}, {"time": "06:30", "flow": -778.8, "fwd_capacity": 1800.0, "rev_capacity": 1800.0, "fwd_free": 1657.52, "rev_free": 421.2, "fwd_split": "2078.72", "rev_split": "分断あり"}, {"time": "07:00", "flow": -857.6, "fwd_capacity": 1800.0, "rev_capacity": 1800.0, "fwd_free": 1694.32, "rev_free": 342.4, "fwd_split": "2036.72", "rev_split": "分断あり"}, {"time": "07:30", "flow": -975.7, "fwd_capacity": 1800.0, "rev_capacity": 1800.0, "fwd_free": 1719.32, "rev_free": 224.3, "fwd_split": "1752.589", "rev_split": "分断なし"}, {"time": "08:00", "flow": -1080.6, "fwd_capacity": 1800.0, "rev_capacity": 1800.0, "fwd_free": 1751.02, "rev_free": 119.4, "fwd_split": "1364.675", "rev_split": "分断なし"}, {"time": "08:30", "flow": -1036.0, "fwd_capacity": 1800.0, "rev_capacity": 1800.0, "fwd_free": 1792.02, "rev_free": 164.0, "fwd_split": "1956.02", "rev_split": "分断あり"}, {"time": "09:00", "flow": -871.5, "fwd_capacity": 1800.0, "rev_capacity": 1800.0, "fwd_free": 1789.42, "rev_free": 328.5, "fwd_split": "1599.858", "rev_split": "分断なし"}, {"time": "09:30", "flow": -702.6, "fwd_capacity": 1800.0, "rev_capacity": 1800.0, "fwd_free": 1902.6, "rev_free": 497.4, "fwd_split": "1311.562", "rev_split": "分断なし"}, {"time": "10:00", "flow": -804.3, "fwd_capacity": 1800.0, "rev_capacity": 1800.0, "fwd_free": 1995.37, "rev_free": 395.7, "fwd_split": "298.815", "rev_split": "分断なし"}, {"time": "10:30", "flow": -1145.8, "fwd_capacity": 1800.0, "rev_capacity": 1800.0, "fwd_free": 2222.165, "rev_free": 54.2, "fwd_split": "155.608", "rev_split": "分断なし"}, {"time": "11:00", "flow": -1195.0, "fwd_capacity": 1800.0, "rev_capacity": 1800.0, "fwd_free": 2276.365, "rev_free": 5.0, "fwd_split": "871.005", "rev_split": "分断なし"}, {"time": "11:30", "flow": -1169.9, "fwd_capacity": 1800.0, "rev_capacity": 1800.0, "fwd_free": 2237.665, "rev_free": 30.1, "fwd_split": "740.981", "rev_split": "分断なし"}, {"time": "12:00", "flow": -1200.0, "fwd_capacity": 1800.0, "rev_capacity": 1800.0, "fwd_free": 2371.438, "rev_free": 0.0, "fwd_split": "689.456", "rev_split": "分断なし"}, {"time": "12:30", "flow": -1130.3, "fwd_capacity": 1800.0, "rev_capacity": 1800.0, "fwd_free": 2132.004, "rev_free": 69.7, "fwd_split": "546.806", "rev_split": "分断なし"}, {"time": "13:00", "flow": -1185.0, "fwd_capacity": 1800.0, "rev_capacity": 1800.0, "fwd_free": 2186.704, "rev_free": 15.0, "fwd_split": "648.827", "rev_split": "分断なし"}, {"time": "13:30", "flow": -1118.5, "fwd_capacity": 1800.0, "rev_capacity": 1800.0, "fwd_free": 2089.204, "rev_free": 81.5, "fwd_split": "1236.443", "rev_split": "分断なし"}, {"time": "14:00", "flow": -1085.1, "fwd_capacity": 1800.0, "rev_capacity": 1800.0, "fwd_free": 2045.804, "rev_free": 114.9, "fwd_split": "1674.384", "rev_split": "分断なし"}, {"time": "14:30", "flow": -1130.0, "fwd_capacity": 1800.0, "rev_capacity": 1800.0, "fwd_free": 2330.0, "rev_free": 70.0, "fwd_split": "1966.706", "rev_split": "分断なし"}, {"time": "15:00", "flow": -1176.0, "fwd_capacity": 1800.0, "rev_capacity": 1800.0, "fwd_free": 2342.221, "rev_free": 24.0, "fwd_split": "2236.486", "rev_split": "分断なし"}, {"time": "15:30", "flow": -1198.9, "fwd_capacity": 1800.0, "rev_capacity": 1800.0, "fwd_free": 2398.9, "rev_free": 1.1, "fwd_split": "2087.553", "rev_split": "分断なし"}, {"time": "16:00", "flow": -919.7, "fwd_capacity": 1800.0, "rev_capacity": 1800.0, "fwd_free": 1935.054, "rev_free": 280.3, "fwd_split": "1266.19", "rev_split": "分断なし"}, {"time": "16:30", "flow": 15.4, "fwd_capacity": 1800.0, "rev_capacity": 1800.0, "fwd_free": 1184.6, "rev_free": 966.59, "fwd_split": "791.6", "rev_split": "分断なし"}, {"time": "17:00", "flow": 282.6, "fwd_capacity": 1800.0, "rev_capacity": 1800.0, "fwd_free": 917.4, "rev_free": 1455.6, "fwd_split": "823.473", "rev_split": "分断なし"}, {"time": "17:30", "flow": 284.1, "fwd_capacity": 1800.0, "rev_capacity": 1800.0, "fwd_free": 915.9, "rev_free": 1484.1, "fwd_split": "1351.629", "rev_split": "分断なし"}, {"time": "18:00", "flow": 490.7, "fwd_capacity": 1800.0, "rev_capacity": 1800.0, "fwd_free": 709.3, "rev_free": 1690.7, "fwd_split": "1367.166", "rev_split": "分断なし"}, {"time": "18:30", "flow": 511.4, "fwd_capacity": 1800.0, "rev_capacity": 1800.0, "fwd_free": 688.6, "rev_free": 1710.4, "fwd_split": "840.167", "rev_split": "分断なし"}, {"time": "19:00", "flow": 598.9, "fwd_capacity": 1800.0, "rev_capacity": 1800.0, "fwd_free": 601.1, "rev_free": 1798.9, "fwd_split": "925.735", "rev_split": "分断なし"}, {"time": "19:30", "flow": 112.8, "fwd_capacity": 1800.0, "rev_capacity": 1800.0, "fwd_free": 1087.2, "rev_free": 1312.8, "fwd_split": "774.22", "rev_split": "分断なし"}, {"time": "20:00", "flow": 72.8, "fwd_capacity": 1800.0, "rev_capacity": 1800.0, "fwd_free": 1127.2, "rev_free": 1272.8, "fwd_split": "1161.576", "rev_split": "分断なし"}, {"time": "20:30", "flow": 198.4, "fwd_capacity": 1800.0, "rev_capacity": 1800.0, "fwd_free": 1001.6, "rev_free": 1398.4, "fwd_split": "1511.352", "rev_split": "分断なし"}, {"time": "21:00", "flow": 177.8, "fwd_capacity": 1800.0, "rev_capacity": 1800.0, "fwd_free": 1022.2, "rev_free": 1377.8, "fwd_split": "1714.813", "rev_split": "分断なし"}, {"time": "21:30", "flow": 208.7, "fwd_capacity": 1800.0, "rev_capacity": 1800.0, "fwd_free": 991.3, "rev_free": 1408.7, "fwd_split": "2322.024", "rev_split": "分断なし"}, {"time": "22:00", "flow": 63.5, "fwd_capacity": 1800.0, "rev_capacity": 1800.0, "fwd_free": 1136.5, "rev_free": 1263.5, "fwd_split": "2400", "rev_split": "分断あり"}, {"time": "22:30", "flow": -27.1, "fwd_capacity": 1800.0, "rev_capacity": 1800.0, "fwd_free": 1227.1, "rev_free": 1172.9, "fwd_split": "2400", "rev_split": "分断あり"}, {"time": "23:00", "flow": -307.3, "fwd_capacity": 1800.0, "rev_capacity": 1800.0, "fwd_free": 1507.3, "rev_free": 892.7, "fwd_split": "2400", "rev_split": "分断あり"}, {"time": "23:30", "flow": -344.0, "fwd_capacity": 1800.0, "rev_capacity": 1800.0, "fwd_free": 1544.0, "rev_free": 856.0, "fwd_split": "2400", "rev_split": "分断あり"}, {"time": "24:00", "flow": -637.6, "fwd_capacity": 1800.0, "rev_capacity": 1800.0, "fwd_free": 1837.6, "rev_free": 562.4, "fwd_split": "2400", "rev_split": "分断あり"}], "中部フェンス": [{"time": "00:30", "flow": -3010.0, "fwd_capacity": 2500.0, "rev_capacity": 3010.0, "fwd_free": 5479.359, "rev_free": 0.0, "fwd_split": "1215.13", "rev_split": "分断なし"}, {"time": "01:00", "flow": -3010.0, "fwd_capacity": 2500.0, "rev_capacity": 3010.0, "fwd_free": 5479.47, "rev_free": 0.0, "fwd_split": "1240.065", "rev_split": "分断なし"}, {"time": "01:30", "flow": -3010.0, "fwd_capacity": 2500.0, "rev_capacity": 3010.0, "fwd_free": 5426.081, "rev_free": 0.0, "fwd_split": "1159.162", "rev_split": "分断なし"}, {"time": "02:00", "flow": -3008.8, "fwd_capacity": 2500.0, "rev_capacity": 3010.0, "fwd_free": 5428.517, "rev_free": 1.2, "fwd_split": "1072.92", "rev_split": "分断なし"}, {"time": "02:30", "flow": -3010.0, "fwd_capacity": 2500.0, "rev_capacity": 3010.0, "fwd_free": 5480.47, "rev_free": 0.0, "fwd_split": "1032.567", "rev_split": "分断なし"}, {"time": "03:00", "flow": -3007.8, "fwd_capacity": 2500.0, "rev_capacity": 3010.0, "fwd_free": 5397.203, "rev_free": 2.2, "fwd_split": "1078.033", "rev_split": "分断なし"}, {"time": "03:30", "flow": -3010.0, "fwd_capacity": 2500.0, "rev_capacity": 3010.0, "fwd_free": 5392.403, "rev_free": 0.0, "fwd_split": "1302.231", "rev_split": "分断なし"}, {"time": "04:00", "flow": -3010.0, "fwd_capacity": 2500.0, "rev_capacity": 3010.0, "fwd_free": 5398.403, "rev_free": 0.0, "fwd_split": "1243.583", "rev_split": "分断なし"}, {"time": "04:30", "flow": -3010.0, "fwd_capacity": 2500.0, "rev_capacity": 3010.0, "fwd_free": 5321.983, "rev_free": 0.0, "fwd_split": "1323.463", "rev_split": "分断なし"}, {"time": "05:00", "flow": -3010.0, "fwd_capacity": 2500.0, "rev_capacity": 3010.0, "fwd_free": 5269.807, "rev_free": 0.0, "fwd_split": "1258.588", "rev_split": "分断なし"}, {"time": "05:30", "flow": -3010.0, "fwd_capacity": 2500.0, "rev_capacity": 3010.0, "fwd_free": 5397.688, "rev_free": 0.0, "fwd_split": "1419.937", "rev_split": "分断なし"}, {"time": "06:00", "flow": -3010.0, "fwd_capacity": 2500.0, "rev_capacity": 3010.0, "fwd_free": 5254.807, "rev_free": 0.0, "fwd_split": "1538.481", "rev_split": "分断なし"}, {"time": "06:30", "flow": -3005.1, "fwd_capacity": 2500.0, "rev_capacity": 3010.0, "fwd_free": 5157.488, "rev_free": 4.9, "fwd_split": "1603.372", "rev_split": "分断なし"}, {"time": "07:00", "flow": -3009.1, "fwd_capacity": 2500.0, "rev_capacity": 3010.0, "fwd_free": 5070.075, "rev_free": 0.9, "fwd_split": "1929.949", "rev_split": "分断なし"}, {"time": "07:30", "flow": -2999.9, "fwd_capacity": 2300.0, "rev_capacity": 3010.0, "fwd_free": 4805.487, "rev_free": 10.1, "fwd_split": "1818.17", "rev_split": "分断なし"}, {"time": "08:00", "flow": -2992.8, "fwd_capacity": 2300.0, "rev_capacity": 3010.0, "fwd_free": 4454.212, "rev_free": 17.2, "fwd_split": "1380.745", "rev_split": "分断なし"}, {"time": "08:30", "flow": -3010.0, "fwd_capacity": 2530.0, "rev_capacity": 3010.0, "fwd_free": 4846.903, "rev_free": 0.0, "fwd_split": "1753.676", "rev_split": "分断なし"}, {"time": "09:00", "flow": -3010.0, "fwd_capacity": 2530.0, "rev_capacity": 3010.0, "fwd_free": 5008.803, "rev_free": 0.0, "fwd_split": "1385.803", "rev_split": "分断なし"}, {"time": "09:30", "flow": -3007.3, "fwd_capacity": 2530.0, "rev_capacity": 3010.0, "fwd_free": 5303.558, "rev_free": 2.7, "fwd_split": "961.701", "rev_split": "分断なし"}, {"time": "10:00", "flow": -3010.0, "fwd_capacity": 2530.0, "rev_capacity": 3010.0, "fwd_free": 5307.358, "rev_free": 0.0, "fwd_split": "170.006", "rev_split": "分断なし"}, {"time": "10:30", "flow": -2975.5, "fwd_capacity": 2530.0, "rev_capacity": 3010.0, "fwd_free": 5275.789, "rev_free": 34.5, "fwd_split": "583.939", "rev_split": "分断なし"}, {"time": "11:00", "flow": -2912.4, "fwd_capacity": 2530.0, "rev_capacity": 3010.0, "fwd_free": 5235.876, "rev_free": 97.6, "fwd_split": "1027.199", "rev_split": "分断なし"}, {"time": "11:30", "flow": -2876.5, "fwd_capacity": 2530.0, "rev_capacity": 3010.0, "fwd_free": 5201.982, "rev_free": 133.5, "fwd_split": "820.214", "rev_split": "分断なし"}, {"time": "12:00", "flow": -2909.8, "fwd_capacity": 2530.0, "rev_capacity": 3010.0, "fwd_free": 5196.695, "rev_free": 100.2, "fwd_split": "638.44", "rev_split": "分断なし"}, {"time": "12:30", "flow": -2993.8, "fwd_capacity": 2530.0, "rev_capacity": 3010.0, "fwd_free": 5395.465, "rev_free": 16.2, "fwd_split": "926.949", "rev_split": "分断なし"}, {"time": "13:00", "flow": -2980.1, "fwd_capacity": 2530.0, "rev_capacity": 3010.0, "fwd_free": 5386.886, "rev_free": 29.9, "fwd_split": "1242.381", "rev_split": "分断なし"}, {"time": "13:30", "flow": -2753.5, "fwd_capacity": 2530.0, "rev_capacity": 3010.0, "fwd_free": 5112.161, "rev_free": 256.5, "fwd_split": "930.464", "rev_split": "分断なし"}, {"time": "14:00", "flow": -2867.2, "fwd_capacity": 2530.0, "rev_capacity": 3010.0, "fwd_free": 5201.31, "rev_free": 142.8, "fwd_split": "1185.846", "rev_split": "分断なし"}, {"time": "14:30", "flow": -2869.4, "fwd_capacity": 2530.0, "rev_capacity": 3010.0, "fwd_free": 5077.817, "rev_free": 140.6, "fwd_split": "1451.705", "rev_split": "分断なし"}, {"time": "15:00", "flow": -3010.0, "fwd_capacity": 2530.0, "rev_capacity": 3010.0, "fwd_free": 5237.0, "rev_free": 0.0, "fwd_split": "1702.14", "rev_split": "分断なし"}, {"time": "15:30", "flow": -3010.0, "fwd_capacity": 2530.0, "rev_capacity": 3010.0, "fwd_free": 5069.141, "rev_free": 0.0, "fwd_split": "1680.721", "rev_split": "分断なし"}, {"time": "16:00", "flow": -3010.0, "fwd_capacity": 2530.0, "rev_capacity": 3010.0, "fwd_free": 5267.911, "rev_free": 0.0, "fwd_split": "895.73", "rev_split": "分断なし"}, {"time": "16:30", "flow": -3010.0, "fwd_capacity": 2530.0, "rev_capacity": 3010.0, "fwd_free": 5144.629, "rev_free": 0.0, "fwd_split": "43.742", "rev_split": "分断なし"}, {"time": "17:00", "flow": -3010.0, "fwd_capacity": 2530.0, "rev_capacity": 3010.0, "fwd_free": 4903.093, "rev_free": 0.0, "fwd_split": "0", "rev_split": "分断なし"}, {"time": "17:30", "flow": -3010.0, "fwd_capacity": 2530.0, "rev_capacity": 3010.0, "fwd_free": 5243.303, "rev_free": 0.0, "fwd_split": "427.155", "rev_split": "分断なし"}, {"time": "18:00", "flow": -3010.0, "fwd_capacity": 2530.0, "rev_capacity": 3010.0, "fwd_free": 5149.755, "rev_free": 0.0, "fwd_split": "419.318", "rev_split": "分断なし"}, {"time": "18:30", "flow": -3010.0, "fwd_capacity": 2730.0, "rev_capacity": 3010.0, "fwd_free": 5077.698, "rev_free": 0.0, "fwd_split": "0", "rev_split": "分断なし"}, {"time": "19:00", "flow": -3010.0, "fwd_capacity": 2730.0, "rev_capacity": 3010.0, "fwd_free": 5103.331, "rev_free": 0.0, "fwd_split": "0", "rev_split": "分断なし"}, {"time": "19:30", "flow": -3010.0, "fwd_capacity": 2730.0, "rev_capacity": 3010.0, "fwd_free": 5075.621, "rev_free": 0.0, "fwd_split": "36.158", "rev_split": "分断なし"}, {"time": "20:00", "flow": -3010.0, "fwd_capacity": 2730.0, "rev_capacity": 3010.0, "fwd_free": 5082.567, "rev_free": 0.0, "fwd_split": "294.684", "rev_split": "分断なし"}, {"time": "20:30", "flow": -3010.0, "fwd_capacity": 2730.0, "rev_capacity": 3010.0, "fwd_free": 5272.507, "rev_free": 0.0, "fwd_split": "255.283", "rev_split": "分断なし"}, {"time": "21:00", "flow": -3010.0, "fwd_capacity": 2730.0, "rev_capacity": 3010.0, "fwd_free": 5152.398, "rev_free": 0.0, "fwd_split": "413.891", "rev_split": "分断なし"}, {"time": "21:30", "flow": -3010.0, "fwd_capacity": 2730.0, "rev_capacity": 3010.0, "fwd_free": 5250.317, "rev_free": 0.0, "fwd_split": "819.533", "rev_split": "分断なし"}, {"time": "22:00", "flow": -3010.0, "fwd_capacity": 2730.0, "rev_capacity": 3010.0, "fwd_free": 5200.087, "rev_free": 0.0, "fwd_split": "975.391", "rev_split": "分断なし"}, {"time": "22:30", "flow": -3010.0, "fwd_capacity": 2500.0, "rev_capacity": 3010.0, "fwd_free": 4894.087, "rev_free": 0.0, "fwd_split": "1029.861", "rev_split": "分断なし"}, {"time": "23:00", "flow": -3010.0, "fwd_capacity": 2500.0, "rev_capacity": 3010.0, "fwd_free": 4851.512, "rev_free": 0.0, "fwd_split": "1123.887", "rev_split": "分断なし"}, {"time": "23:30", "flow": -3010.0, "fwd_capacity": 2500.0, "rev_capacity": 3010.0, "fwd_free": 4902.584, "rev_free": 0.0, "fwd_split": "1142.686", "rev_split": "分断なし"}, {"time": "24:00", "flow": -3010.0, "fwd_capacity": 2500.0, "rev_capacity": 3010.0, "fwd_free": 4888.845, "rev_free": 0.0, "fwd_split": "1350.403", "rev_split": "分断なし"}], "北陸フェンス": [{"time": "00:30", "flow": -686.9, "fwd_capacity": 2400.0, "rev_capacity": 3570.0, "fwd_free": 3048.9, "rev_free": 2857.1, "fwd_split": "3044.086", "rev_split": "分断なし"}, {"time": "01:00", "flow": -497.3, "fwd_capacity": 2400.0, "rev_capacity": 3570.0, "fwd_free": 2886.75, "rev_free": 3046.7, "fwd_split": "3153.555", "rev_split": "分断なし"}, {"time": "01:30", "flow": -486.4, "fwd_capacity": 2400.0, "rev_capacity": 3570.0, "fwd_free": 2886.4, "rev_free": 3009.521, "fwd_split": "3238.304", "rev_split": "分断なし"}, {"time": "02:00", "flow": -357.4, "fwd_capacity": 2400.0, "rev_capacity": 3570.0, "fwd_free": 2757.4, "rev_free": 3159.249, "fwd_split": "3226.008", "rev_split": "分断なし"}, {"time": "02:30", "flow": -231.2, "fwd_capacity": 2400.0, "rev_capacity": 3570.0, "fwd_free": 2631.2, "rev_free": 3310.063, "fwd_split": "3305.624", "rev_split": "分断なし"}, {"time": "03:00", "flow": -216.0, "fwd_capacity": 2400.0, "rev_capacity": 3570.0, "fwd_free": 2611.626, "rev_free": 3328.0, "fwd_split": "3302.641", "rev_split": "分断なし"}, {"time": "03:30", "flow": -581.3, "fwd_capacity": 2400.0, "rev_capacity": 3570.0, "fwd_free": 2949.3, "rev_free": 2977.268, "fwd_split": "3268.856", "rev_split": "分断なし"}, {"time": "04:00", "flow": -562.0, "fwd_capacity": 2400.0, "rev_capacity": 3570.0, "fwd_free": 2929.676, "rev_free": 2982.0, "fwd_split": "3207.445", "rev_split": "分断なし"}, {"time": "04:30", "flow": -527.8, "fwd_capacity": 2400.0, "rev_capacity": 3570.0, "fwd_free": 2892.8, "rev_free": 3016.2, "fwd_split": "3213.777", "rev_split": "分断なし"}, {"time": "05:00", "flow": -583.9, "fwd_capacity": 2400.0, "rev_capacity": 3570.0, "fwd_free": 2948.9, "rev_free": 2960.1, "fwd_split": "3187.173", "rev_split": "分断なし"}, {"time": "05:30", "flow": -578.7, "fwd_capacity": 2400.0, "rev_capacity": 3570.0, "fwd_free": 2943.7, "rev_free": 2965.3, "fwd_split": "3195.287", "rev_split": "分断なし"}, {"time": "06:00", "flow": -649.2, "fwd_capacity": 2400.0, "rev_capacity": 3570.0, "fwd_free": 3014.2, "rev_free": 2903.538, "fwd_split": "3171.443", "rev_split": "分断なし"}, {"time": "06:30", "flow": -531.6, "fwd_capacity": 2400.0, "rev_capacity": 3570.0, "fwd_free": 2872.6, "rev_free": 3023.634, "fwd_split": "3146.133", "rev_split": "分断なし"}, {"time": "07:00", "flow": -461.8, "fwd_capacity": 2400.0, "rev_capacity": 3570.0, "fwd_free": 2789.8, "rev_free": 3090.186, "fwd_split": "3212.429", "rev_split": "分断なし"}, {"time": "07:30", "flow": -550.0, "fwd_capacity": 2400.0, "rev_capacity": 3470.0, "fwd_free": 2869.109, "rev_free": 2916.07, "fwd_split": "3227.006", "rev_split": "分断なし"}, {"time": "08:00", "flow": -509.7, "fwd_capacity": 2400.0, "rev_capacity": 3470.0, "fwd_free": 2784.63, "rev_free": 2933.236, "fwd_split": "3301.815", "rev_split": "分断なし"}, {"time": "08:30", "flow": -169.9, "fwd_capacity": 2820.0, "rev_capacity": 3470.0, "fwd_free": 2865.522, "rev_free": 3300.1, "fwd_split": "3398.498", "rev_split": "分断なし"}, {"time": "09:00", "flow": -148.9, "fwd_capacity": 2820.0, "rev_capacity": 3470.0, "fwd_free": 2919.832, "rev_free": 3321.1, "fwd_split": "3585.09", "rev_split": "分断なし"}, {"time": "09:30", "flow": -16.2, "fwd_capacity": 2820.0, "rev_capacity": 3470.0, "fwd_free": 2793.13, "rev_free": 3453.8, "fwd_split": "3637.587", "rev_split": "分断なし"}, {"time": "10:00", "flow": -86.1, "fwd_capacity": 2820.0, "rev_capacity": 3470.0, "fwd_free": 2863.03, "rev_free": 3383.9, "fwd_split": "3605.613", "rev_split": "分断なし"}, {"time": "10:30", "flow": -47.1, "fwd_capacity": 2820.0, "rev_capacity": 3470.0, "fwd_free": 2824.03, "rev_free": 3422.9, "fwd_split": "3668.56", "rev_split": "分断なし"}, {"time": "11:00", "flow": -145.0, "fwd_capacity": 2820.0, "rev_capacity": 3470.0, "fwd_free": 2960.849, "rev_free": 3315.599, "fwd_split": "3617.822", "rev_split": "分断なし"}, {"time": "11:30", "flow": -321.4, "fwd_capacity": 2820.0, "rev_capacity": 3470.0, "fwd_free": 3091.255, "rev_free": 3141.525, "fwd_split": "3450.493", "rev_split": "分断なし"}, {"time": "12:00", "flow": -344.6, "fwd_capacity": 2820.0, "rev_capacity": 3470.0, "fwd_free": 3121.31, "rev_free": 3125.4, "fwd_split": "3419.161", "rev_split": "分断なし"}, {"time": "12:30", "flow": -194.1, "fwd_capacity": 2820.0, "rev_capacity": 3470.0, "fwd_free": 3014.03, "rev_free": 3275.9, "fwd_split": "3618.316", "rev_split": "分断なし"}, {"time": "13:00", "flow": -189.0, "fwd_capacity": 2820.0, "rev_capacity": 3470.0, "fwd_free": 3008.93, "rev_free": 3281.0, "fwd_split": "3632.793", "rev_split": "分断なし"}, {"time": "13:30", "flow": -355.2, "fwd_capacity": 2820.0, "rev_capacity": 3470.0, "fwd_free": 3057.13, "rev_free": 3114.8, "fwd_split": "3468.917", "rev_split": "分断なし"}, {"time": "14:00", "flow": -307.1, "fwd_capacity": 2820.0, "rev_capacity": 3470.0, "fwd_free": 3018.466, "rev_free": 3161.97, "fwd_split": "3492.88", "rev_split": "分断なし"}, {"time": "14:30", "flow": -277.9, "fwd_capacity": 2820.0, "rev_capacity": 3470.0, "fwd_free": 2987.708, "rev_free": 3192.1, "fwd_split": "3592.195", "rev_split": "分断なし"}, {"time": "15:00", "flow": -144.3, "fwd_capacity": 2820.0, "rev_capacity": 3470.0, "fwd_free": 2839.16, "rev_free": 3325.7, "fwd_split": "3679.832", "rev_split": "分断なし"}, {"time": "15:30", "flow": -61.9, "fwd_capacity": 2820.0, "rev_capacity": 3470.0, "fwd_free": 2788.278, "rev_free": 3408.1, "fwd_split": "3739.417", "rev_split": "分断なし"}, {"time": "16:00", "flow": -102.8, "fwd_capacity": 2820.0, "rev_capacity": 3470.0, "fwd_free": 2808.73, "rev_free": 3367.2, "fwd_split": "3635.57", "rev_split": "分断なし"}, {"time": "16:30", "flow": -255.6, "fwd_capacity": 2820.0, "rev_capacity": 3470.0, "fwd_free": 2953.55, "rev_free": 3214.4, "fwd_split": "3434.053", "rev_split": "分断なし"}, {"time": "17:00", "flow": -194.8, "fwd_capacity": 2820.0, "rev_capacity": 3470.0, "fwd_free": 2900.406, "rev_free": 3275.2, "fwd_split": "3505.159", "rev_split": "分断なし"}, {"time": "17:30", "flow": -228.1, "fwd_capacity": 2820.0, "rev_capacity": 3470.0, "fwd_free": 2940.03, "rev_free": 3241.9, "fwd_split": "3483.701", "rev_split": "分断なし"}, {"time": "18:00", "flow": -219.9, "fwd_capacity": 2820.0, "rev_capacity": 3470.0, "fwd_free": 2934.83, "rev_free": 3250.1, "fwd_split": "3439.149", "rev_split": "分断なし"}, {"time": "18:30", "flow": -185.5, "fwd_capacity": 2820.0, "rev_capacity": 3570.0, "fwd_free": 2924.43, "rev_free": 3384.5, "fwd_split": "3571.537", "rev_split": "分断なし"}, {"time": "19:00", "flow": -160.1, "fwd_capacity": 2820.0, "rev_capacity": 3570.0, "fwd_free": 2899.03, "rev_free": 3409.9, "fwd_split": "3596.061", "rev_split": "分断なし"}, {"time": "19:30", "flow": -192.2, "fwd_capacity": 2820.0, "rev_capacity": 3570.0, "fwd_free": 2931.13, "rev_free": 3377.8, "fwd_split": "3539.432", "rev_split": "分断なし"}, {"time": "20:00", "flow": -276.7, "fwd_capacity": 2820.0, "rev_capacity": 3570.0, "fwd_free": 3015.63, "rev_free": 3293.3, "fwd_split": "3482.112", "rev_split": "分断なし"}, {"time": "20:30", "flow": -246.4, "fwd_capacity": 2820.0, "rev_capacity": 3570.0, "fwd_free": 2987.33, "rev_free": 3323.6, "fwd_split": "3553.809", "rev_split": "分断なし"}, {"time": "21:00", "flow": -297.0, "fwd_capacity": 2820.0, "rev_capacity": 3570.0, "fwd_free": 3038.93, "rev_free": 3273.0, "fwd_split": "3505.706", "rev_split": "分断なし"}, {"time": "21:30", "flow": -248.6, "fwd_capacity": 2820.0, "rev_capacity": 3570.0, "fwd_free": 2988.53, "rev_free": 3321.4, "fwd_split": "3578.836", "rev_split": "分断なし"}, {"time": "22:00", "flow": -287.4, "fwd_capacity": 2820.0, "rev_capacity": 3570.0, "fwd_free": 3060.4, "rev_free": 3280.6, "fwd_split": "3558.453", "rev_split": "分断なし"}, {"time": "22:30", "flow": -255.4, "fwd_capacity": 2400.0, "rev_capacity": 3570.0, "fwd_free": 2606.4, "rev_free": 3310.67, "fwd_split": "3578.197", "rev_split": "分断なし"}, {"time": "23:00", "flow": -356.6, "fwd_capacity": 2400.0, "rev_capacity": 3570.0, "fwd_free": 2677.53, "rev_free": 3213.4, "fwd_split": "3487.972", "rev_split": "分断なし"}, {"time": "23:30", "flow": -416.0, "fwd_capacity": 2400.0, "rev_capacity": 3570.0, "fwd_free": 2748.608, "rev_free": 3154.0, "fwd_split": "3420.285", "rev_split": "分断なし"}, {"time": "24:00", "flow": -477.6, "fwd_capacity": 2400.0, "rev_capacity": 3570.0, "fwd_free": 2820.07, "rev_free": 3092.4, "fwd_split": "3377.946", "rev_split": "分断なし"}], "関西フェンス": [{"time": "00:30", "flow": -2323.1, "fwd_capacity": 2500.0, "rev_capacity": 3010.0, "fwd_free": 4789.459, "rev_free": 671.9, "fwd_split": "1700.044", "rev_split": "分断なし"}, {"time": "01:00", "flow": -2512.7, "fwd_capacity": 2500.0, "rev_capacity": 3010.0, "fwd_free": 4966.72, "rev_free": 497.3, "fwd_split": "1630.51", "rev_split": "分断なし"}, {"time": "01:30", "flow": -2523.6, "fwd_capacity": 2500.0, "rev_capacity": 3010.0, "fwd_free": 4865.602, "rev_free": 486.4, "fwd_split": "1416.779", "rev_split": "分断なし"}, {"time": "02:00", "flow": -2651.4, "fwd_capacity": 2500.0, "rev_capacity": 3010.0, "fwd_free": 5017.766, "rev_free": 358.6, "fwd_split": "1363.561", "rev_split": "分断なし"}, {"time": "02:30", "flow": -2778.8, "fwd_capacity": 2500.0, "rev_capacity": 3010.0, "fwd_free": 5220.533, "rev_free": 231.2, "fwd_split": "1268.206", "rev_split": "分断なし"}, {"time": "03:00", "flow": -2791.8, "fwd_capacity": 2500.0, "rev_capacity": 3010.0, "fwd_free": 5159.577, "rev_free": 218.2, "fwd_split": "1319.392", "rev_split": "分断なし"}, {"time": "03:30", "flow": -2428.7, "fwd_capacity": 2500.0, "rev_capacity": 3010.0, "fwd_free": 4831.671, "rev_free": 581.3, "fwd_split": "1591.943", "rev_split": "分断なし"}, {"time": "04:00", "flow": -2448.0, "fwd_capacity": 2500.0, "rev_capacity": 3010.0, "fwd_free": 4842.727, "rev_free": 562.0, "fwd_split": "1580.138", "rev_split": "分断なし"}, {"time": "04:30", "flow": -2482.2, "fwd_capacity": 2500.0, "rev_capacity": 3010.0, "fwd_free": 4803.183, "rev_free": 527.8, "fwd_split": "1653.686", "rev_split": "分断なし"}, {"time": "05:00", "flow": -2426.1, "fwd_capacity": 2500.0, "rev_capacity": 3010.0, "fwd_free": 4694.907, "rev_free": 583.9, "fwd_split": "1615.415", "rev_split": "分断なし"}, {"time": "05:30", "flow": -2431.3, "fwd_capacity": 2500.0, "rev_capacity": 3010.0, "fwd_free": 4827.302, "rev_free": 578.014, "fwd_split": "1767.964", "rev_split": "分断なし"}, {"time": "06:00", "flow": -2360.8, "fwd_capacity": 2500.0, "rev_capacity": 3010.0, "fwd_free": 4623.345, "rev_free": 649.2, "fwd_split": "1919.776", "rev_split": "分断なし"}, {"time": "06:30", "flow": -2473.5, "fwd_capacity": 2500.0, "rev_capacity": 3010.0, "fwd_free": 4670.122, "rev_free": 536.5, "fwd_split": "2012.473", "rev_split": "分断なし"}, {"time": "07:00", "flow": -2547.3, "fwd_capacity": 2500.0, "rev_capacity": 3010.0, "fwd_free": 4662.261, "rev_free": 462.7, "fwd_split": "2269.506", "rev_split": "分断なし"}, {"time": "07:30", "flow": -2449.9, "fwd_capacity": 2300.0, "rev_capacity": 3010.0, "fwd_free": 4332.448, "rev_free": 560.1, "fwd_split": "2057.234", "rev_split": "分断なし"}, {"time": "08:00", "flow": -2483.1, "fwd_capacity": 2300.0, "rev_capacity": 3010.0, "fwd_free": 4042.518, "rev_free": 526.9, "fwd_split": "1521.866", "rev_split": "分断なし"}, {"time": "08:30", "flow": -2840.1, "fwd_capacity": 2530.0, "rev_capacity": 3010.0, "fwd_free": 4801.381, "rev_free": 169.9, "fwd_split": "1825.178", "rev_split": "分断なし"}, {"time": "09:00", "flow": -2861.1, "fwd_capacity": 2530.0, "rev_capacity": 3010.0, "fwd_free": 4908.971, "rev_free": 148.9, "fwd_split": "1270.713", "rev_split": "分断なし"}, {"time": "09:30", "flow": -2991.1, "fwd_capacity": 2530.0, "rev_capacity": 3010.0, "fwd_free": 5330.428, "rev_free": 18.9, "fwd_split": "794.114", "rev_split": "分断なし"}, {"time": "10:00", "flow": -2923.9, "fwd_capacity": 2530.0, "rev_capacity": 3010.0, "fwd_free": 5264.328, "rev_free": 86.1, "fwd_split": "34.393", "rev_split": "分断なし"}, {"time": "10:30", "flow": -2928.4, "fwd_capacity": 2530.0, "rev_capacity": 3010.0, "fwd_free": 5271.759, "rev_free": 81.6, "fwd_split": "385.379", "rev_split": "分断なし"}, {"time": "11:00", "flow": -2767.4, "fwd_capacity": 2530.0, "rev_capacity": 3010.0, "fwd_free": 5085.626, "rev_free": 242.6, "fwd_split": "869.976", "rev_split": "分断なし"}, {"time": "11:30", "flow": -2555.1, "fwd_capacity": 2530.0, "rev_capacity": 3010.0, "fwd_free": 4923.652, "rev_free": 454.9, "fwd_split": "832.646", "rev_split": "分断なし"}, {"time": "12:00", "flow": -2565.2, "fwd_capacity": 2530.0, "rev_capacity": 3010.0, "fwd_free": 4895.385, "rev_free": 444.8, "fwd_split": "689.279", "rev_split": "分断なし"}, {"time": "12:30", "flow": -2799.7, "fwd_capacity": 2530.0, "rev_capacity": 3010.0, "fwd_free": 5201.435, "rev_free": 210.3, "fwd_split": "778.633", "rev_split": "分断なし"}, {"time": "13:00", "flow": -2791.1, "fwd_capacity": 2530.0, "rev_capacity": 3010.0, "fwd_free": 5197.956, "rev_free": 218.9, "fwd_split": "1079.588", "rev_split": "分断なし"}, {"time": "13:30", "flow": -2398.3, "fwd_capacity": 2530.0, "rev_capacity": 3010.0, "fwd_free": 4875.031, "rev_free": 611.7, "fwd_split": "931.547", "rev_split": "分断なし"}, {"time": "14:00", "flow": -2560.1, "fwd_capacity": 2530.0, "rev_capacity": 3010.0, "fwd_free": 5001.914, "rev_free": 449.9, "fwd_split": "1162.036", "rev_split": "分断なし"}, {"time": "14:30", "flow": -2591.5, "fwd_capacity": 2530.0, "rev_capacity": 3010.0, "fwd_free": 4910.109, "rev_free": 418.5, "fwd_split": "1329.51", "rev_split": "分断なし"}, {"time": "15:00", "flow": -2865.7, "fwd_capacity": 2530.0, "rev_capacity": 3010.0, "fwd_free": 5217.84, "rev_free": 144.3, "fwd_split": "1492.308", "rev_split": "分断なし"}, {"time": "15:30", "flow": -2948.1, "fwd_capacity": 2530.0, "rev_capacity": 3010.0, "fwd_free": 5100.863, "rev_free": 61.9, "fwd_split": "1411.304", "rev_split": "分断なし"}, {"time": "16:00", "flow": -2907.2, "fwd_capacity": 2530.0, "rev_capacity": 3010.0, "fwd_free": 5279.181, "rev_free": 102.8, "fwd_split": "730.16", "rev_split": "分断なし"}, {"time": "16:30", "flow": -2754.4, "fwd_capacity": 2530.0, "rev_capacity": 3010.0, "fwd_free": 5011.079, "rev_free": 255.6, "fwd_split": "79.689", "rev_split": "分断なし"}, {"time": "17:00", "flow": -2815.2, "fwd_capacity": 2530.0, "rev_capacity": 3010.0, "fwd_free": 4822.687, "rev_free": 194.8, "fwd_split": "0", "rev_split": "分断なし"}, {"time": "17:30", "flow": -2781.9, "fwd_capacity": 2530.0, "rev_capacity": 3010.0, "fwd_free": 5123.273, "rev_free": 228.1, "fwd_split": "413.454", "rev_split": "分断なし"}, {"time": "18:00", "flow": -2790.1, "fwd_capacity": 2530.0, "rev_capacity": 3010.0, "fwd_free": 5034.925, "rev_free": 219.9, "fwd_split": "450.169", "rev_split": "分断なし"}, {"time": "18:30", "flow": -2824.5, "fwd_capacity": 2730.0, "rev_capacity": 3010.0, "fwd_free": 4973.268, "rev_free": 185.5, "fwd_split": "0", "rev_split": "分断なし"}, {"time": "19:00", "flow": -2849.9, "fwd_capacity": 2730.0, "rev_capacity": 3010.0, "fwd_free": 5024.301, "rev_free": 160.1, "fwd_split": "0", "rev_split": "分断なし"}, {"time": "19:30", "flow": -2817.8, "fwd_capacity": 2730.0, "rev_capacity": 3010.0, "fwd_free": 4964.491, "rev_free": 192.2, "fwd_split": "66.726", "rev_split": "分断なし"}, {"time": "20:00", "flow": -2733.3, "fwd_capacity": 2730.0, "rev_capacity": 3010.0, "fwd_free": 4886.937, "rev_free": 276.7, "fwd_split": "382.572", "rev_split": "分断なし"}, {"time": "20:30", "flow": -2763.6, "fwd_capacity": 2730.0, "rev_capacity": 3010.0, "fwd_free": 5105.177, "rev_free": 246.4, "fwd_split": "271.474", "rev_split": "分断なし"}, {"time": "21:00", "flow": -2713.0, "fwd_capacity": 2730.0, "rev_capacity": 3010.0, "fwd_free": 4933.468, "rev_free": 297.0, "fwd_split": "478.185", "rev_split": "分断なし"}, {"time": "21:30", "flow": -2761.4, "fwd_capacity": 2730.0, "rev_capacity": 3010.0, "fwd_free": 5081.787, "rev_free": 248.6, "fwd_split": "810.697", "rev_split": "分断なし"}, {"time": "22:00", "flow": -2722.6, "fwd_capacity": 2730.0, "rev_capacity": 3010.0, "fwd_free": 4957.687, "rev_free": 287.4, "fwd_split": "984.938", "rev_split": "分断なし"}, {"time": "22:30", "flow": -2754.6, "fwd_capacity": 2500.0, "rev_capacity": 3010.0, "fwd_free": 4683.757, "rev_free": 255.4, "fwd_split": "1017.734", "rev_split": "分断なし"}, {"time": "23:00", "flow": -2653.4, "fwd_capacity": 2500.0, "rev_capacity": 3010.0, "fwd_free": 4573.982, "rev_free": 356.6, "fwd_split": "1205.915", "rev_split": "分断なし"}, {"time": "23:30", "flow": -2594.0, "fwd_capacity": 2500.0, "rev_capacity": 3010.0, "fwd_free": 4553.976, "rev_free": 416.0, "fwd_split": "1292.401", "rev_split": "分断なし"}, {"time": "24:00", "flow": -2532.4, "fwd_capacity": 2500.0, "rev_capacity": 3010.0, "fwd_free": 4468.775, "rev_free": 477.6, "fwd_split": "1542.457", "rev_split": "分断なし"}], "関西-中国（東）": [{"time": "00:30", "flow": -2639.564, "fwd_capacity": 4700.0, "rev_capacity": 4650.0, "fwd_free": 7295.604, "rev_free": 1991.65, "fwd_split": "2448.961", "rev_split": "分断なし"}, {"time": "01:00", "flow": -2478.564, "fwd_capacity": 4700.0, "rev_capacity": 4650.0, "fwd_free": 7134.594, "rev_free": 2109.712, "fwd_split": "2551.181", "rev_split": "分断なし"}, {"time": "01:30", "flow": -1624.188, "fwd_capacity": 4700.0, "rev_capacity": 4650.0, "fwd_free": 6298.199, "rev_free": 2946.657, "fwd_split": "3024.28", "rev_split": "分断なし"}, {"time": "02:00", "flow": -1663.584, "fwd_capacity": 4700.0, "rev_capacity": 4650.0, "fwd_free": 6337.595, "rev_free": 2927.097, "fwd_split": "2866.566", "rev_split": "分断なし"}, {"time": "02:30", "flow": -1855.992, "fwd_capacity": 4700.0, "rev_capacity": 4650.0, "fwd_free": 6532.003, "rev_free": 2684.958, "fwd_split": "2599.585", "rev_split": "分断なし"}, {"time": "03:00", "flow": -2045.286, "fwd_capacity": 4700.0, "rev_capacity": 4650.0, "fwd_free": 6721.286, "rev_free": 2529.456, "fwd_split": "2547.265", "rev_split": "分断なし"}, {"time": "03:30", "flow": -2420.114, "fwd_capacity": 4700.0, "rev_capacity": 4650.0, "fwd_free": 7057.74, "rev_free": 2189.656, "fwd_split": "2380.441", "rev_split": "分断なし"}, {"time": "04:00", "flow": -2416.616, "fwd_capacity": 4700.0, "rev_capacity": 4650.0, "fwd_free": 7060.566, "rev_free": 2204.569, "fwd_split": "2444.449", "rev_split": "分断なし"}, {"time": "04:30", "flow": -2396.784, "fwd_capacity": 4700.0, "rev_capacity": 4650.0, "fwd_free": 6970.79, "rev_free": 2221.142, "fwd_split": "2635.217", "rev_split": "分断なし"}, {"time": "05:00", "flow": -2346.988, "fwd_capacity": 4700.0, "rev_capacity": 4650.0, "fwd_free": 6865.018, "rev_free": 2260.778, "fwd_split": "2641.471", "rev_split": "分断なし"}, {"time": "05:30", "flow": -2420.85, "fwd_capacity": 4700.0, "rev_capacity": 4650.0, "fwd_free": 7079.79, "rev_free": 2199.598, "fwd_split": "2694.253", "rev_split": "分断なし"}, {"time": "06:00", "flow": -2350.832, "fwd_capacity": 4700.0, "rev_capacity": 4650.0, "fwd_free": 6856.862, "rev_free": 2261.43, "fwd_split": "2742.971", "rev_split": "分断なし"}, {"time": "06:30", "flow": -2501.726, "fwd_capacity": 4700.0, "rev_capacity": 4650.0, "fwd_free": 7024.643, "rev_free": 2144.55, "fwd_split": "2628.776", "rev_split": "分断なし"}, {"time": "07:00", "flow": -2521.184, "fwd_capacity": 4700.0, "rev_capacity": 4650.0, "fwd_free": 7074.137, "rev_free": 2125.896, "fwd_split": "2460.777", "rev_split": "分断なし"}, {"time": "07:30", "flow": -2791.062, "fwd_capacity": 4700.0, "rev_capacity": 4650.0, "fwd_free": 7363.5, "rev_free": 1846.718, "fwd_split": "1721.217", "rev_split": "分断なし"}, {"time": "08:00", "flow": -3438.524, "fwd_capacity": 4700.0, "rev_capacity": 4650.0, "fwd_free": 7685.319, "rev_free": 1170.648, "fwd_split": "649.975", "rev_split": "分断なし"}, {"time": "08:30", "flow": -4238.124, "fwd_capacity": 4700.0, "rev_capacity": 4650.0, "fwd_free": 8586.782, "rev_free": 350.722, "fwd_split": "975.735", "rev_split": "分断なし"}, {"time": "09:00", "flow": -4509.94, "fwd_capacity": 4700.0, "rev_capacity": 4650.0, "fwd_free": 8973.961, "rev_free": 60.96, "fwd_split": "516.779", "rev_split": "分断なし"}, {"time": "09:30", "flow": -4423.346, "fwd_capacity": 4700.0, "rev_capacity": 4650.0, "fwd_free": 8852.36, "rev_free": 148.52, "fwd_split": "276.189", "rev_split": "分断なし"}, {"time": "10:00", "flow": -4518.686, "fwd_capacity": 4700.0, "rev_capacity": 4650.0, "fwd_free": 8837.7, "rev_free": 46.5, "fwd_split": "0", "rev_split": "分断なし"}, {"time": "10:30", "flow": -4495.75, "fwd_capacity": 4700.0, "rev_capacity": 4650.0, "fwd_free": 8788.764, "rev_free": 74.44, "fwd_split": "0", "rev_split": "分断なし"}, {"time": "11:00", "flow": -4497.116, "fwd_capacity": 4700.0, "rev_capacity": 4650.0, "fwd_free": 8783.127, "rev_free": 78.74, "fwd_split": "0", "rev_split": "分断なし"}, {"time": "11:30", "flow": -4573.762, "fwd_capacity": 4700.0, "rev_capacity": 4650.0, "fwd_free": 8890.773, "rev_free": 0.0, "fwd_split": "0", "rev_split": "分断なし"}, {"time": "12:00", "flow": -4533.61, "fwd_capacity": 4700.0, "rev_capacity": 4650.0, "fwd_free": 8797.993, "rev_free": 36.82, "fwd_split": "0", "rev_split": "分断なし"}, {"time": "12:30", "flow": -4562.676, "fwd_capacity": 4700.0, "rev_capacity": 4650.0, "fwd_free": 8863.614, "rev_free": 0.064, "fwd_split": "0", "rev_split": "分断なし"}, {"time": "13:00", "flow": -4549.83, "fwd_capacity": 4700.0, "rev_capacity": 4650.0, "fwd_free": 9124.841, "rev_free": 10.762, "fwd_split": "0", "rev_split": "分断なし"}, {"time": "13:30", "flow": -4561.062, "fwd_capacity": 4700.0, "rev_capacity": 4650.0, "fwd_free": 8687.073, "rev_free": 0.066, "fwd_split": "0", "rev_split": "分断なし"}, {"time": "14:00", "flow": -4545.928, "fwd_capacity": 4700.0, "rev_capacity": 4650.0, "fwd_free": 8937.939, "rev_free": 0.0, "fwd_split": "58.994", "rev_split": "分断なし"}, {"time": "14:30", "flow": -4566.67, "fwd_capacity": 4700.0, "rev_capacity": 4650.0, "fwd_free": 9037.375, "rev_free": 0.06, "fwd_split": "324.27", "rev_split": "分断なし"}, {"time": "15:00", "flow": -4567.628, "fwd_capacity": 4700.0, "rev_capacity": 4650.0, "fwd_free": 9094.642, "rev_free": 0.06, "fwd_split": "883.014", "rev_split": "分断なし"}, {"time": "15:30", "flow": -4388.22, "fwd_capacity": 4700.0, "rev_capacity": 4650.0, "fwd_free": 8832.44, "rev_free": 176.96, "fwd_split": "1260.597", "rev_split": "分断なし"}, {"time": "16:00", "flow": -4405.134, "fwd_capacity": 4700.0, "rev_capacity": 4650.0, "fwd_free": 8810.164, "rev_free": 178.228, "fwd_split": "911.006", "rev_split": "分断なし"}, {"time": "16:30", "flow": -3449.636, "fwd_capacity": 4700.0, "rev_capacity": 4650.0, "fwd_free": 7925.964, "rev_free": 1177.536, "fwd_split": "1582.034", "rev_split": "分断なし"}, {"time": "17:00", "flow": -3189.046, "fwd_capacity": 4700.0, "rev_capacity": 4650.0, "fwd_free": 7583.553, "rev_free": 1457.498, "fwd_split": "1693.452", "rev_split": "分断なし"}, {"time": "17:30", "flow": -2639.748, "fwd_capacity": 4700.0, "rev_capacity": 4650.0, "fwd_free": 7227.615, "rev_free": 1950.221, "fwd_split": "2336.757", "rev_split": "分断なし"}, {"time": "18:00", "flow": -2304.312, "fwd_capacity": 4700.0, "rev_capacity": 4650.0, "fwd_free": 6914.638, "rev_free": 2281.01, "fwd_split": "2407.832", "rev_split": "分断なし"}, {"time": "18:30", "flow": -2056.188, "fwd_capacity": 4700.0, "rev_capacity": 4650.0, "fwd_free": 6348.877, "rev_free": 2558.438, "fwd_split": "2676.19", "rev_split": "分断なし"}, {"time": "19:00", "flow": -1796.644, "fwd_capacity": 4700.0, "rev_capacity": 4650.0, "fwd_free": 6114.966, "rev_free": 2808.712, "fwd_split": "2866.793", "rev_split": "分断なし"}, {"time": "19:30", "flow": -1661.714, "fwd_capacity": 4700.0, "rev_capacity": 4650.0, "fwd_free": 5952.326, "rev_free": 2970.404, "fwd_split": "3158.878", "rev_split": "分断なし"}, {"time": "20:00", "flow": -1581.558, "fwd_capacity": 4700.0, "rev_capacity": 4650.0, "fwd_free": 5871.434, "rev_free": 3017.422, "fwd_split": "3439.919", "rev_split": "分断なし"}, {"time": "20:30", "flow": -1878.756, "fwd_capacity": 4700.0, "rev_capacity": 4650.0, "fwd_free": 6346.262, "rev_free": 2730.356, "fwd_split": "3427.803", "rev_split": "分断なし"}, {"time": "21:00", "flow": -2112.126, "fwd_capacity": 4700.0, "rev_capacity": 4650.0, "fwd_free": 6456.813, "rev_free": 2511.11, "fwd_split": "3269.006", "rev_split": "分断なし"}, {"time": "21:30", "flow": -2514.618, "fwd_capacity": 4700.0, "rev_capacity": 4650.0, "fwd_free": 6872.856, "rev_free": 2127.632, "fwd_split": "3076.705", "rev_split": "分断なし"}, {"time": "22:00", "flow": -2626.444, "fwd_capacity": 4700.0, "rev_capacity": 4650.0, "fwd_free": 6924.784, "rev_free": 2019.802, "fwd_split": "3020.465", "rev_split": "分断なし"}, {"time": "22:30", "flow": -2613.75, "fwd_capacity": 4700.0, "rev_capacity": 4650.0, "fwd_free": 6919.794, "rev_free": 2024.926, "fwd_split": "3046.163", "rev_split": "分断なし"}, {"time": "23:00", "flow": -2576.76, "fwd_capacity": 4700.0, "rev_capacity": 4650.0, "fwd_free": 6887.115, "rev_free": 2060.248, "fwd_split": "3110.159", "rev_split": "分断なし"}, {"time": "23:30", "flow": -3032.332, "fwd_capacity": 4700.0, "rev_capacity": 4650.0, "fwd_free": 7376.195, "rev_free": 1614.33, "fwd_split": "2665.361", "rev_split": "分断なし"}, {"time": "24:00", "flow": -2851.804, "fwd_capacity": 4700.0, "rev_capacity": 4650.0, "fwd_free": 7219.838, "rev_free": 1797.302, "fwd_split": "2929.116", "rev_split": "分断なし"}], "関西-中国（西）": [{"time": "00:30", "flow": -2047.452, "fwd_capacity": 4700.0, "rev_capacity": 4650.0, "fwd_free": 6703.492, "rev_free": 2583.762, "fwd_split": "3085.073", "rev_split": "分断なし"}, {"time": "01:00", "flow": -1893.432, "fwd_capacity": 4700.0, "rev_capacity": 4650.0, "fwd_free": 6549.462, "rev_free": 2694.844, "fwd_split": "3181.213", "rev_split": "分断なし"}, {"time": "01:30", "flow": -1045.964, "fwd_capacity": 4700.0, "rev_capacity": 4650.0, "fwd_free": 5719.975, "rev_free": 3524.881, "fwd_split": "3646.504", "rev_split": "分断なし"}, {"time": "02:00", "flow": -1324.702, "fwd_capacity": 4700.0, "rev_capacity": 4650.0, "fwd_free": 5998.713, "rev_free": 3265.979, "fwd_split": "3524.148", "rev_split": "分断なし"}, {"time": "02:30", "flow": -1537.388, "fwd_capacity": 4700.0, "rev_capacity": 4650.0, "fwd_free": 6213.399, "rev_free": 3003.562, "fwd_split": "3237.789", "rev_split": "分断なし"}, {"time": "03:00", "flow": -1462.538, "fwd_capacity": 4700.0, "rev_capacity": 4650.0, "fwd_free": 6138.538, "rev_free": 3112.204, "fwd_split": "3172.913", "rev_split": "分断なし"}, {"time": "03:30", "flow": -1821.862, "fwd_capacity": 4700.0, "rev_capacity": 4650.0, "fwd_free": 6459.488, "rev_free": 2787.908, "fwd_split": "3017.693", "rev_split": "分断なし"}, {"time": "04:00", "flow": -1832.67, "fwd_capacity": 4700.0, "rev_capacity": 4650.0, "fwd_free": 6476.62, "rev_free": 2788.515, "fwd_split": "3065.395", "rev_split": "分断なし"}, {"time": "04:30", "flow": -1844.636, "fwd_capacity": 4700.0, "rev_capacity": 4650.0, "fwd_free": 6418.642, "rev_free": 2773.29, "fwd_split": "3228.365", "rev_split": "分断なし"}, {"time": "05:00", "flow": -1816.984, "fwd_capacity": 4700.0, "rev_capacity": 4650.0, "fwd_free": 6335.014, "rev_free": 2790.782, "fwd_split": "3212.475", "rev_split": "分断なし"}, {"time": "05:30", "flow": -1874.722, "fwd_capacity": 4700.0, "rev_capacity": 4650.0, "fwd_free": 6533.662, "rev_free": 2745.726, "fwd_split": "3240.381", "rev_split": "分断なし"}, {"time": "06:00", "flow": -1755.204, "fwd_capacity": 4700.0, "rev_capacity": 4650.0, "fwd_free": 6261.234, "rev_free": 2857.058, "fwd_split": "3387.599", "rev_split": "分断なし"}, {"time": "06:30", "flow": -1836.718, "fwd_capacity": 4700.0, "rev_capacity": 4650.0, "fwd_free": 6359.635, "rev_free": 2809.558, "fwd_split": "3301.784", "rev_split": "分断なし"}, {"time": "07:00", "flow": -1797.644, "fwd_capacity": 4700.0, "rev_capacity": 4650.0, "fwd_free": 6350.597, "rev_free": 2849.436, "fwd_split": "3184.317", "rev_split": "分断なし"}, {"time": "07:30", "flow": -1987.092, "fwd_capacity": 4700.0, "rev_capacity": 4650.0, "fwd_free": 6559.53, "rev_free": 2650.688, "fwd_split": "2525.187", "rev_split": "分断なし"}, {"time": "08:00", "flow": -2823.614, "fwd_capacity": 4700.0, "rev_capacity": 4650.0, "fwd_free": 7070.409, "rev_free": 1785.558, "fwd_split": "1503.085", "rev_split": "分断なし"}, {"time": "08:30", "flow": -3520.424, "fwd_capacity": 4700.0, "rev_capacity": 4650.0, "fwd_free": 7869.082, "rev_free": 1068.422, "fwd_split": "1856.835", "rev_split": "分断なし"}, {"time": "09:00", "flow": -3687.536, "fwd_capacity": 4700.0, "rev_capacity": 4650.0, "fwd_free": 8151.557, "rev_free": 883.364, "fwd_split": "1400.783", "rev_split": "分断なし"}, {"time": "09:30", "flow": -3514.926, "fwd_capacity": 4700.0, "rev_capacity": 4650.0, "fwd_free": 7943.94, "rev_free": 1056.94, "fwd_split": "1211.609", "rev_split": "分断なし"}, {"time": "10:00", "flow": -3576.152, "fwd_capacity": 4700.0, "rev_capacity": 4650.0, "fwd_free": 7895.166, "rev_free": 989.034, "fwd_split": "604.548", "rev_split": "分断なし"}, {"time": "10:30", "flow": -3517.638, "fwd_capacity": 4700.0, "rev_capacity": 4650.0, "fwd_free": 7810.652, "rev_free": 1052.552, "fwd_split": "573.126", "rev_split": "分断なし"}, {"time": "11:00", "flow": -3478.106, "fwd_capacity": 4700.0, "rev_capacity": 4650.0, "fwd_free": 7764.117, "rev_free": 1097.75, "fwd_split": "607.335", "rev_split": "分断なし"}, {"time": "11:30", "flow": -3535.39, "fwd_capacity": 4700.0, "rev_capacity": 4650.0, "fwd_free": 7852.401, "rev_free": 1038.372, "fwd_split": "655.383", "rev_split": "分断なし"}, {"time": "12:00", "flow": -3454.768, "fwd_capacity": 4700.0, "rev_capacity": 4650.0, "fwd_free": 7719.151, "rev_free": 1115.662, "fwd_split": "684.154", "rev_split": "分断なし"}, {"time": "12:30", "flow": -3391.266, "fwd_capacity": 4700.0, "rev_capacity": 4650.0, "fwd_free": 7692.204, "rev_free": 1171.474, "fwd_split": "783.348", "rev_split": "分断なし"}, {"time": "13:00", "flow": -3369.24, "fwd_capacity": 4700.0, "rev_capacity": 4650.0, "fwd_free": 7944.251, "rev_free": 1191.352, "fwd_split": "1066.601", "rev_split": "分断なし"}, {"time": "13:30", "flow": -3445.922, "fwd_capacity": 4700.0, "rev_capacity": 4650.0, "fwd_free": 7571.933, "rev_free": 1115.206, "fwd_split": "552.151", "rev_split": "分断なし"}, {"time": "14:00", "flow": -3452.718, "fwd_capacity": 4700.0, "rev_capacity": 4650.0, "fwd_free": 7844.729, "rev_free": 1093.21, "fwd_split": "1162.204", "rev_split": "分断なし"}, {"time": "14:30", "flow": -3482.222, "fwd_capacity": 4700.0, "rev_capacity": 4650.0, "fwd_free": 7952.927, "rev_free": 1084.508, "fwd_split": "1419.718", "rev_split": "分断なし"}, {"time": "15:00", "flow": -3532.29, "fwd_capacity": 4700.0, "rev_capacity": 4650.0, "fwd_free": 8059.304, "rev_free": 1035.398, "fwd_split": "1928.352", "rev_split": "分断なし"}, {"time": "15:30", "flow": -3428.88, "fwd_capacity": 4700.0, "rev_capacity": 4650.0, "fwd_free": 7873.1, "rev_free": 1136.3, "fwd_split": "2228.937", "rev_split": "分断なし"}, {"time": "16:00", "flow": -3527.104, "fwd_capacity": 4700.0, "rev_capacity": 4650.0, "fwd_free": 7932.134, "rev_free": 1056.258, "fwd_split": "1789.036", "rev_split": "分断なし"}, {"time": "16:30", "flow": -2717.99, "fwd_capacity": 4700.0, "rev_capacity": 4650.0, "fwd_free": 7194.318, "rev_free": 1909.182, "fwd_split": "2313.68", "rev_split": "分断なし"}, {"time": "17:00", "flow": -2569.754, "fwd_capacity": 4700.0, "rev_capacity": 4650.0, "fwd_free": 6964.261, "rev_free": 2076.79, "fwd_split": "2312.744", "rev_split": "分断なし"}, {"time": "17:30", "flow": -2138.83, "fwd_capacity": 4700.0, "rev_capacity": 4650.0, "fwd_free": 6726.697, "rev_free": 2451.139, "fwd_split": "2837.675", "rev_split": "分断なし"}, {"time": "18:00", "flow": -1871.522, "fwd_capacity": 4700.0, "rev_capacity": 4650.0, "fwd_free": 6481.848, "rev_free": 2713.8, "fwd_split": "2848.622", "rev_split": "分断なし"}, {"time": "18:30", "flow": -1700.05, "fwd_capacity": 4700.0, "rev_capacity": 4650.0, "fwd_free": 5992.739, "rev_free": 2914.576, "fwd_split": "3044.328", "rev_split": "分断なし"}, {"time": "19:00", "flow": -1457.314, "fwd_capacity": 4700.0, "rev_capacity": 4650.0, "fwd_free": 5775.636, "rev_free": 3148.042, "fwd_split": "3310.123", "rev_split": "分断なし"}, {"time": "19:30", "flow": -1344.648, "fwd_capacity": 4700.0, "rev_capacity": 4650.0, "fwd_free": 5635.26, "rev_free": 3287.47, "fwd_split": "3579.944", "rev_split": "分断なし"}, {"time": "20:00", "flow": -1233.826, "fwd_capacity": 4700.0, "rev_capacity": 4650.0, "fwd_free": 5523.702, "rev_free": 3365.154, "fwd_split": "3842.651", "rev_split": "分断なし"}, {"time": "20:30", "flow": -1506.674, "fwd_capacity": 4700.0, "rev_capacity": 4650.0, "fwd_free": 5974.18, "rev_free": 3102.438, "fwd_split": "3876.885", "rev_split": "分断なし"}, {"time": "21:00", "flow": -1715.516, "fwd_capacity": 4700.0, "rev_capacity": 4650.0, "fwd_free": 6060.203, "rev_free": 2907.72, "fwd_split": "3738.616", "rev_split": "分断なし"}, {"time": "21:30", "flow": -2083.796, "fwd_capacity": 4700.0, "rev_capacity": 4650.0, "fwd_free": 6442.034, "rev_free": 2558.454, "fwd_split": "3566.527", "rev_split": "分断なし"}, {"time": "22:00", "flow": -2164.03, "fwd_capacity": 4700.0, "rev_capacity": 4650.0, "fwd_free": 6462.37, "rev_free": 2482.216, "fwd_split": "3539.879", "rev_split": "分断なし"}, {"time": "22:30", "flow": -2134.112, "fwd_capacity": 4700.0, "rev_capacity": 4650.0, "fwd_free": 6440.156, "rev_free": 2504.564, "fwd_split": "3582.801", "rev_split": "分断なし"}, {"time": "23:00", "flow": -2080.016, "fwd_capacity": 4700.0, "rev_capacity": 4650.0, "fwd_free": 6390.371, "rev_free": 2556.992, "fwd_split": "3662.903", "rev_split": "分断なし"}, {"time": "23:30", "flow": -2491.778, "fwd_capacity": 4700.0, "rev_capacity": 4650.0, "fwd_free": 6835.641, "rev_free": 2154.884, "fwd_split": "3257.915", "rev_split": "分断なし"}, {"time": "24:00", "flow": -2297.72, "fwd_capacity": 4700.0, "rev_capacity": 4650.0, "fwd_free": 6665.754, "rev_free": 2351.386, "fwd_split": "3533.2", "rev_split": "分断なし"}], "阿南紀北直流幹線": [{"time": "00:30", "flow": -930.0, "fwd_capacity": 0.0, "rev_capacity": 930.0, "fwd_free": 930.0, "rev_free": 0.0, "fwd_split": "0", "rev_split": "分断なし"}, {"time": "01:00", "flow": -930.0, "fwd_capacity": 0.0, "rev_capacity": 930.0, "fwd_free": 930.0, "rev_free": 0.0, "fwd_split": "0", "rev_split": "分断なし"}, {"time": "01:30", "flow": -930.0, "fwd_capacity": 0.0, "rev_capacity": 930.0, "fwd_free": 930.0, "rev_free": 0.0, "fwd_split": "0", "rev_split": "分断なし"}, {"time": "02:00", "flow": -930.0, "fwd_capacity": 0.0, "rev_capacity": 930.0, "fwd_free": 930.0, "rev_free": 0.0, "fwd_split": "0", "rev_split": "分断なし"}, {"time": "02:30", "flow": -930.0, "fwd_capacity": 0.0, "rev_capacity": 930.0, "fwd_free": 930.0, "rev_free": 0.0, "fwd_split": "0", "rev_split": "分断なし"}, {"time": "03:00", "flow": -930.0, "fwd_capacity": 0.0, "rev_capacity": 930.0, "fwd_free": 930.0, "rev_free": 0.0, "fwd_split": "0", "rev_split": "分断なし"}, {"time": "03:30", "flow": -930.0, "fwd_capacity": 0.0, "rev_capacity": 930.0, "fwd_free": 930.0, "rev_free": 0.0, "fwd_split": "0", "rev_split": "分断なし"}, {"time": "04:00", "flow": -930.0, "fwd_capacity": 0.0, "rev_capacity": 930.0, "fwd_free": 930.0, "rev_free": 0.0, "fwd_split": "0", "rev_split": "分断なし"}, {"time": "04:30", "flow": -930.0, "fwd_capacity": 0.0, "rev_capacity": 930.0, "fwd_free": 930.0, "rev_free": 0.0, "fwd_split": "0", "rev_split": "分断なし"}, {"time": "05:00", "flow": -930.0, "fwd_capacity": 0.0, "rev_capacity": 930.0, "fwd_free": 930.0, "rev_free": 0.0, "fwd_split": "0", "rev_split": "分断なし"}, {"time": "05:30", "flow": -930.0, "fwd_capacity": 0.0, "rev_capacity": 930.0, "fwd_free": 930.0, "rev_free": 0.0, "fwd_split": "0", "rev_split": "分断なし"}, {"time": "06:00", "flow": -930.0, "fwd_capacity": 0.0, "rev_capacity": 930.0, "fwd_free": 930.0, "rev_free": 0.0, "fwd_split": "0", "rev_split": "分断なし"}, {"time": "06:30", "flow": -930.0, "fwd_capacity": 0.0, "rev_capacity": 930.0, "fwd_free": 930.0, "rev_free": 0.0, "fwd_split": "0", "rev_split": "分断なし"}, {"time": "07:00", "flow": -930.0, "fwd_capacity": 0.0, "rev_capacity": 930.0, "fwd_free": 930.0, "rev_free": 0.0, "fwd_split": "0", "rev_split": "分断なし"}, {"time": "07:30", "flow": -930.0, "fwd_capacity": 0.0, "rev_capacity": 930.0, "fwd_free": 930.0, "rev_free": 0.0, "fwd_split": "0", "rev_split": "分断なし"}, {"time": "08:00", "flow": -930.0, "fwd_capacity": 0.0, "rev_capacity": 930.0, "fwd_free": 930.0, "rev_free": 0.0, "fwd_split": "0", "rev_split": "分断なし"}, {"time": "08:30", "flow": -930.0, "fwd_capacity": 0.0, "rev_capacity": 930.0, "fwd_free": 930.0, "rev_free": 0.0, "fwd_split": "0", "rev_split": "分断なし"}, {"time": "09:00", "flow": -930.0, "fwd_capacity": 0.0, "rev_capacity": 930.0, "fwd_free": 930.0, "rev_free": 0.0, "fwd_split": "0", "rev_split": "分断なし"}, {"time": "09:30", "flow": -930.0, "fwd_capacity": 0.0, "rev_capacity": 930.0, "fwd_free": 930.0, "rev_free": 0.0, "fwd_split": "0", "rev_split": "分断なし"}, {"time": "10:00", "flow": -930.0, "fwd_capacity": 0.0, "rev_capacity": 930.0, "fwd_free": 930.0, "rev_free": 0.0, "fwd_split": "0", "rev_split": "分断なし"}, {"time": "10:30", "flow": -930.0, "fwd_capacity": 0.0, "rev_capacity": 930.0, "fwd_free": 930.0, "rev_free": 0.0, "fwd_split": "0", "rev_split": "分断なし"}, {"time": "11:00", "flow": -930.0, "fwd_capacity": 0.0, "rev_capacity": 930.0, "fwd_free": 930.0, "rev_free": 0.0, "fwd_split": "0", "rev_split": "分断なし"}, {"time": "11:30", "flow": -930.0, "fwd_capacity": 0.0, "rev_capacity": 930.0, "fwd_free": 930.0, "rev_free": 0.0, "fwd_split": "0", "rev_split": "分断なし"}, {"time": "12:00", "flow": -930.0, "fwd_capacity": 0.0, "rev_capacity": 930.0, "fwd_free": 930.0, "rev_free": 0.0, "fwd_split": "0", "rev_split": "分断なし"}, {"time": "12:30", "flow": -930.0, "fwd_capacity": 0.0, "rev_capacity": 930.0, "fwd_free": 930.0, "rev_free": 0.0, "fwd_split": "0", "rev_split": "分断なし"}, {"time": "13:00", "flow": -930.0, "fwd_capacity": 0.0, "rev_capacity": 930.0, "fwd_free": 930.0, "rev_free": 0.0, "fwd_split": "0", "rev_split": "分断なし"}, {"time": "13:30", "flow": -930.0, "fwd_capacity": 0.0, "rev_capacity": 930.0, "fwd_free": 930.0, "rev_free": 0.0, "fwd_split": "0", "rev_split": "分断なし"}, {"time": "14:00", "flow": -930.0, "fwd_capacity": 0.0, "rev_capacity": 930.0, "fwd_free": 930.0, "rev_free": 0.0, "fwd_split": "0", "rev_split": "分断なし"}, {"time": "14:30", "flow": -930.0, "fwd_capacity": 0.0, "rev_capacity": 930.0, "fwd_free": 930.0, "rev_free": 0.0, "fwd_split": "0", "rev_split": "分断なし"}, {"time": "15:00", "flow": -930.0, "fwd_capacity": 0.0, "rev_capacity": 930.0, "fwd_free": 930.0, "rev_free": 0.0, "fwd_split": "0", "rev_split": "分断なし"}, {"time": "15:30", "flow": -930.0, "fwd_capacity": 0.0, "rev_capacity": 930.0, "fwd_free": 930.0, "rev_free": 0.0, "fwd_split": "0", "rev_split": "分断なし"}, {"time": "16:00", "flow": -930.0, "fwd_capacity": 0.0, "rev_capacity": 930.0, "fwd_free": 930.0, "rev_free": 0.0, "fwd_split": "0", "rev_split": "分断なし"}, {"time": "16:30", "flow": -930.0, "fwd_capacity": 0.0, "rev_capacity": 930.0, "fwd_free": 930.0, "rev_free": 0.0, "fwd_split": "0", "rev_split": "分断なし"}, {"time": "17:00", "flow": -930.0, "fwd_capacity": 0.0, "rev_capacity": 930.0, "fwd_free": 930.0, "rev_free": 0.0, "fwd_split": "0", "rev_split": "分断なし"}, {"time": "17:30", "flow": -930.0, "fwd_capacity": 0.0, "rev_capacity": 930.0, "fwd_free": 930.0, "rev_free": 0.0, "fwd_split": "0", "rev_split": "分断なし"}, {"time": "18:00", "flow": -930.0, "fwd_capacity": 0.0, "rev_capacity": 930.0, "fwd_free": 930.0, "rev_free": 0.0, "fwd_split": "0", "rev_split": "分断なし"}, {"time": "18:30", "flow": -930.0, "fwd_capacity": 0.0, "rev_capacity": 930.0, "fwd_free": 930.0, "rev_free": 0.0, "fwd_split": "0", "rev_split": "分断なし"}, {"time": "19:00", "flow": -930.0, "fwd_capacity": 0.0, "rev_capacity": 930.0, "fwd_free": 930.0, "rev_free": 0.0, "fwd_split": "0", "rev_split": "分断なし"}, {"time": "19:30", "flow": -930.0, "fwd_capacity": 0.0, "rev_capacity": 930.0, "fwd_free": 930.0, "rev_free": 0.0, "fwd_split": "0", "rev_split": "分断なし"}, {"time": "20:00", "flow": -930.0, "fwd_capacity": 0.0, "rev_capacity": 930.0, "fwd_free": 930.0, "rev_free": 0.0, "fwd_split": "0", "rev_split": "分断なし"}, {"time": "20:30", "flow": -930.0, "fwd_capacity": 0.0, "rev_capacity": 930.0, "fwd_free": 930.0, "rev_free": 0.0, "fwd_split": "0", "rev_split": "分断なし"}, {"time": "21:00", "flow": -930.0, "fwd_capacity": 0.0, "rev_capacity": 930.0, "fwd_free": 930.0, "rev_free": 0.0, "fwd_split": "0", "rev_split": "分断なし"}, {"time": "21:30", "flow": -930.0, "fwd_capacity": 0.0, "rev_capacity": 930.0, "fwd_free": 930.0, "rev_free": 0.0, "fwd_split": "0", "rev_split": "分断なし"}, {"time": "22:00", "flow": -930.0, "fwd_capacity": 0.0, "rev_capacity": 930.0, "fwd_free": 930.0, "rev_free": 0.0, "fwd_split": "0", "rev_split": "分断なし"}, {"time": "22:30", "flow": -930.0, "fwd_capacity": 0.0, "rev_capacity": 930.0, "fwd_free": 930.0, "rev_free": 0.0, "fwd_split": "0", "rev_split": "分断なし"}, {"time": "23:00", "flow": -930.0, "fwd_capacity": 0.0, "rev_capacity": 930.0, "fwd_free": 930.0, "rev_free": 0.0, "fwd_split": "0", "rev_split": "分断なし"}, {"time": "23:30", "flow": -930.0, "fwd_capacity": 0.0, "rev_capacity": 930.0, "fwd_free": 930.0, "rev_free": 0.0, "fwd_split": "0", "rev_split": "分断なし"}, {"time": "24:00", "flow": -930.0, "fwd_capacity": 0.0, "rev_capacity": 930.0, "fwd_free": 930.0, "rev_free": 0.0, "fwd_split": "0", "rev_split": "分断なし"}], "本四連系線": [{"time": "00:30", "flow": -1200.0, "fwd_capacity": 1200.0, "rev_capacity": 1200.0, "fwd_free": 2356.0, "rev_free": 0.0, "fwd_split": "0", "rev_split": "分断なし"}, {"time": "01:00", "flow": -1199.1, "fwd_capacity": 1200.0, "rev_capacity": 1200.0, "fwd_free": 2355.1, "rev_free": 0.9, "fwd_split": "0", "rev_split": "分断なし"}, {"time": "01:30", "flow": -1200.0, "fwd_capacity": 1200.0, "rev_capacity": 1200.0, "fwd_free": 2356.0, "rev_free": 0.0, "fwd_split": "0", "rev_split": "分断なし"}, {"time": "02:00", "flow": -925.3, "fwd_capacity": 1200.0, "rev_capacity": 1200.0, "fwd_free": 2081.3, "rev_free": 274.7, "fwd_split": "0", "rev_split": "分断なし"}, {"time": "02:30", "flow": -922.4, "fwd_capacity": 1200.0, "rev_capacity": 1200.0, "fwd_free": 2080.4, "rev_free": 277.6, "fwd_split": "0", "rev_split": "分断なし"}, {"time": "03:00", "flow": -1199.1, "fwd_capacity": 1200.0, "rev_capacity": 1200.0, "fwd_free": 2357.1, "rev_free": 0.9, "fwd_split": "0", "rev_split": "分断なし"}, {"time": "03:30", "flow": -1200.0, "fwd_capacity": 1200.0, "rev_capacity": 1200.0, "fwd_free": 2361.0, "rev_free": 0.0, "fwd_split": "0", "rev_split": "分断なし"}, {"time": "04:00", "flow": -1200.0, "fwd_capacity": 1200.0, "rev_capacity": 1200.0, "fwd_free": 2363.0, "rev_free": 0.0, "fwd_split": "0", "rev_split": "分断なし"}, {"time": "04:30", "flow": -1200.0, "fwd_capacity": 1200.0, "rev_capacity": 1200.0, "fwd_free": 2359.0, "rev_free": 0.0, "fwd_split": "0", "rev_split": "分断なし"}, {"time": "05:00", "flow": -1200.0, "fwd_capacity": 1200.0, "rev_capacity": 1200.0, "fwd_free": 2359.0, "rev_free": 0.0, "fwd_split": "0", "rev_split": "分断なし"}, {"time": "05:30", "flow": -1200.0, "fwd_capacity": 1200.0, "rev_capacity": 1200.0, "fwd_free": 2400.0, "rev_free": 0.0, "fwd_split": "0", "rev_split": "分断なし"}, {"time": "06:00", "flow": -1200.0, "fwd_capacity": 1200.0, "rev_capacity": 1200.0, "fwd_free": 2351.0, "rev_free": 0.0, "fwd_split": "0", "rev_split": "分断なし"}, {"time": "06:30", "flow": -1200.0, "fwd_capacity": 1200.0, "rev_capacity": 1200.0, "fwd_free": 2392.0, "rev_free": 0.0, "fwd_split": "0", "rev_split": "分断なし"}, {"time": "07:00", "flow": -1200.0, "fwd_capacity": 1200.0, "rev_capacity": 1200.0, "fwd_free": 2400.0, "rev_free": 0.0, "fwd_split": "0", "rev_split": "分断なし"}, {"time": "07:30", "flow": -1200.0, "fwd_capacity": 1200.0, "rev_capacity": 1200.0, "fwd_free": 2400.0, "rev_free": 0.0, "fwd_split": "0", "rev_split": "分断なし"}, {"time": "08:00", "flow": -961.8, "fwd_capacity": 1200.0, "rev_capacity": 1200.0, "fwd_free": 2161.8, "rev_free": 238.2, "fwd_split": "0", "rev_split": "分断なし"}, {"time": "08:30", "flow": -1036.6, "fwd_capacity": 1200.0, "rev_capacity": 1200.0, "fwd_free": 2236.6, "rev_free": 163.4, "fwd_split": "0", "rev_split": "分断なし"}, {"time": "09:00", "flow": -1138.4, "fwd_capacity": 1200.0, "rev_capacity": 1200.0, "fwd_free": 2338.4, "rev_free": 61.6, "fwd_split": "0", "rev_split": "分断なし"}, {"time": "09:30", "flow": -1200.0, "fwd_capacity": 1200.0, "rev_capacity": 1200.0, "fwd_free": 2373.0, "rev_free": 0.0, "fwd_split": "0", "rev_split": "分断なし"}, {"time": "10:00", "flow": -1200.0, "fwd_capacity": 1200.0, "rev_capacity": 1200.0, "fwd_free": 2357.0, "rev_free": 0.0, "fwd_split": "0", "rev_split": "分断なし"}, {"time": "10:30", "flow": -1200.0, "fwd_capacity": 1200.0, "rev_capacity": 1200.0, "fwd_free": 2398.0, "rev_free": 0.0, "fwd_split": "0", "rev_split": "分断なし"}, {"time": "11:00", "flow": -1200.0, "fwd_capacity": 1200.0, "rev_capacity": 1200.0, "fwd_free": 2398.0, "rev_free": 0.0, "fwd_split": "0", "rev_split": "分断なし"}, {"time": "11:30", "flow": -1200.0, "fwd_capacity": 1200.0, "rev_capacity": 1200.0, "fwd_free": 2400.0, "rev_free": 0.0, "fwd_split": "0", "rev_split": "分断なし"}, {"time": "12:00", "flow": -1200.0, "fwd_capacity": 1200.0, "rev_capacity": 1200.0, "fwd_free": 2389.0, "rev_free": 0.0, "fwd_split": "0", "rev_split": "分断なし"}, {"time": "12:30", "flow": -1200.0, "fwd_capacity": 1200.0, "rev_capacity": 1200.0, "fwd_free": 2389.0, "rev_free": 0.0, "fwd_split": "0", "rev_split": "分断なし"}, {"time": "13:00", "flow": -1200.0, "fwd_capacity": 1200.0, "rev_capacity": 1200.0, "fwd_free": 2389.0, "rev_free": 0.0, "fwd_split": "0", "rev_split": "分断なし"}, {"time": "13:30", "flow": -1200.0, "fwd_capacity": 1200.0, "rev_capacity": 1200.0, "fwd_free": 2389.0, "rev_free": 0.0, "fwd_split": "0", "rev_split": "分断なし"}, {"time": "14:00", "flow": -1200.0, "fwd_capacity": 1200.0, "rev_capacity": 1200.0, "fwd_free": 2390.0, "rev_free": 0.0, "fwd_split": "0", "rev_split": "分断なし"}, {"time": "14:30", "flow": -1200.0, "fwd_capacity": 1200.0, "rev_capacity": 1200.0, "fwd_free": 2389.0, "rev_free": 0.0, "fwd_split": "0", "rev_split": "分断なし"}, {"time": "15:00", "flow": -1200.0, "fwd_capacity": 1200.0, "rev_capacity": 1200.0, "fwd_free": 2390.0, "rev_free": 0.0, "fwd_split": "0", "rev_split": "分断なし"}, {"time": "15:30", "flow": -1200.0, "fwd_capacity": 1200.0, "rev_capacity": 1200.0, "fwd_free": 2391.0, "rev_free": 0.0, "fwd_split": "0", "rev_split": "分断なし"}, {"time": "16:00", "flow": -1200.0, "fwd_capacity": 1200.0, "rev_capacity": 1200.0, "fwd_free": 2400.0, "rev_free": 0.0, "fwd_split": "0", "rev_split": "分断なし"}, {"time": "16:30", "flow": -1200.0, "fwd_capacity": 1200.0, "rev_capacity": 1200.0, "fwd_free": 2400.0, "rev_free": 0.0, "fwd_split": "0", "rev_split": "分断なし"}, {"time": "17:00", "flow": -1200.0, "fwd_capacity": 1200.0, "rev_capacity": 1200.0, "fwd_free": 2400.0, "rev_free": 0.0, "fwd_split": "0", "rev_split": "分断なし"}, {"time": "17:30", "flow": -1200.0, "fwd_capacity": 1200.0, "rev_capacity": 1200.0, "fwd_free": 2400.0, "rev_free": 0.0, "fwd_split": "0", "rev_split": "分断なし"}, {"time": "18:00", "flow": -1200.0, "fwd_capacity": 1200.0, "rev_capacity": 1200.0, "fwd_free": 2392.0, "rev_free": 0.0, "fwd_split": "0", "rev_split": "分断なし"}, {"time": "18:30", "flow": -1200.0, "fwd_capacity": 1200.0, "rev_capacity": 1200.0, "fwd_free": 2388.0, "rev_free": 0.0, "fwd_split": "0", "rev_split": "分断なし"}, {"time": "19:00", "flow": -1200.0, "fwd_capacity": 1200.0, "rev_capacity": 1200.0, "fwd_free": 2296.0, "rev_free": 0.0, "fwd_split": "0", "rev_split": "分断なし"}, {"time": "19:30", "flow": -1200.0, "fwd_capacity": 1200.0, "rev_capacity": 1200.0, "fwd_free": 2296.0, "rev_free": 0.0, "fwd_split": "0", "rev_split": "分断なし"}, {"time": "20:00", "flow": -1200.0, "fwd_capacity": 1200.0, "rev_capacity": 1200.0, "fwd_free": 2345.0, "rev_free": 0.0, "fwd_split": "0", "rev_split": "分断なし"}, {"time": "20:30", "flow": -1200.0, "fwd_capacity": 1200.0, "rev_capacity": 1200.0, "fwd_free": 2323.0, "rev_free": 0.0, "fwd_split": "0", "rev_split": "分断なし"}, {"time": "21:00", "flow": -1200.0, "fwd_capacity": 1200.0, "rev_capacity": 1200.0, "fwd_free": 2327.0, "rev_free": 0.0, "fwd_split": "0", "rev_split": "分断なし"}, {"time": "21:30", "flow": -1200.0, "fwd_capacity": 1200.0, "rev_capacity": 1200.0, "fwd_free": 2341.0, "rev_free": 0.0, "fwd_split": "0", "rev_split": "分断なし"}, {"time": "22:00", "flow": -1200.0, "fwd_capacity": 1200.0, "rev_capacity": 1200.0, "fwd_free": 2343.0, "rev_free": 0.0, "fwd_split": "0", "rev_split": "分断なし"}, {"time": "22:30", "flow": -1200.0, "fwd_capacity": 1200.0, "rev_capacity": 1200.0, "fwd_free": 2343.0, "rev_free": 0.0, "fwd_split": "0", "rev_split": "分断なし"}, {"time": "23:00", "flow": -1200.0, "fwd_capacity": 1200.0, "rev_capacity": 1200.0, "fwd_free": 2344.0, "rev_free": 0.0, "fwd_split": "0", "rev_split": "分断なし"}, {"time": "23:30", "flow": -1200.0, "fwd_capacity": 1200.0, "rev_capacity": 1200.0, "fwd_free": 2348.0, "rev_free": 0.0, "fwd_split": "0", "rev_split": "分断なし"}, {"time": "24:00", "flow": -1200.0, "fwd_capacity": 1200.0, "rev_capacity": 1200.0, "fwd_free": 2350.0, "rev_free": 0.0, "fwd_split": "0", "rev_split": "分断なし"}], "関門連系線": [{"time": "00:30", "flow": -787.8, "fwd_capacity": 850.0, "rev_capacity": 2100.0, "fwd_free": 1613.726, "rev_free": 1312.2, "fwd_split": "1660.384", "rev_split": "分断なし"}, {"time": "01:00", "flow": -645.2, "fwd_capacity": 840.0, "rev_capacity": 2050.0, "fwd_free": 1434.2, "rev_free": 1404.8, "fwd_split": "1733.729", "rev_split": "分断なし"}, {"time": "01:30", "flow": -235.6, "fwd_capacity": 830.0, "rev_capacity": 2010.0, "fwd_free": 1042.646, "rev_free": 1774.4, "fwd_split": "1764.308", "rev_split": "分断なし"}, {"time": "02:00", "flow": -240.7, "fwd_capacity": 830.0, "rev_capacity": 2000.0, "fwd_free": 1043.482, "rev_free": 1759.3, "fwd_split": "1668.344", "rev_split": "分断なし"}, {"time": "02:30", "flow": -246.5, "fwd_capacity": 830.0, "rev_capacity": 2000.0, "fwd_free": 1019.5, "rev_free": 1753.5, "fwd_split": "1620.143", "rev_split": "分断なし"}, {"time": "03:00", "flow": -43.8, "fwd_capacity": 830.0, "rev_capacity": 2000.0, "fwd_free": 863.038, "rev_free": 1956.2, "fwd_split": "1633.401", "rev_split": "分断なし"}, {"time": "03:30", "flow": -616.7, "fwd_capacity": 840.0, "rev_capacity": 2020.0, "fwd_free": 1407.998, "rev_free": 1403.3, "fwd_split": "1391.272", "rev_split": "分断なし"}, {"time": "04:00", "flow": -639.3, "fwd_capacity": 850.0, "rev_capacity": 2050.0, "fwd_free": 1447.916, "rev_free": 1410.7, "fwd_split": "1499.168", "rev_split": "分断なし"}, {"time": "04:30", "flow": -752.5, "fwd_capacity": 860.0, "rev_capacity": 2060.0, "fwd_free": 1503.102, "rev_free": 1307.5, "fwd_split": "1606.561", "rev_split": "分断なし"}, {"time": "05:00", "flow": -832.9, "fwd_capacity": 870.0, "rev_capacity": 2080.0, "fwd_free": 1549.16, "rev_free": 1247.1, "fwd_split": "1525.312", "rev_split": "分断なし"}, {"time": "05:30", "flow": -864.7, "fwd_capacity": 870.0, "rev_capacity": 2080.0, "fwd_free": 1671.244, "rev_free": 1215.3, "fwd_split": "1534.011", "rev_split": "分断なし"}, {"time": "06:00", "flow": -465.9, "fwd_capacity": 840.0, "rev_capacity": 2080.0, "fwd_free": 1150.184, "rev_free": 1614.1, "fwd_split": "1940.256", "rev_split": "分断なし"}, {"time": "06:30", "flow": -654.6, "fwd_capacity": 800.0, "rev_capacity": 2110.0, "fwd_free": 1304.994, "rev_free": 1455.4, "fwd_split": "1665.013", "rev_split": "分断なし"}, {"time": "07:00", "flow": -798.2, "fwd_capacity": 770.0, "rev_capacity": 2140.0, "fwd_free": 1469.715, "rev_free": 1341.8, "fwd_split": "1573.031", "rev_split": "分断なし"}, {"time": "07:30", "flow": -1084.1, "fwd_capacity": 740.0, "rev_capacity": 2240.0, "fwd_free": 1763.1, "rev_free": 1155.9, "fwd_split": "1188.201", "rev_split": "分断なし"}, {"time": "08:00", "flow": -1588.3, "fwd_capacity": 740.0, "rev_capacity": 2350.0, "fwd_free": 1949.874, "rev_free": 761.7, "fwd_split": "611.399", "rev_split": "分断なし"}, {"time": "08:30", "flow": -2130.2, "fwd_capacity": 720.0, "rev_capacity": 2710.0, "fwd_free": 2604.426, "rev_free": 579.8, "fwd_split": "1108.81", "rev_split": "分断なし"}, {"time": "09:00", "flow": -2247.0, "fwd_capacity": 690.0, "rev_capacity": 2710.0, "fwd_free": 2791.734, "rev_free": 449.0, "fwd_split": "731.188", "rev_split": "分断なし"}, {"time": "09:30", "flow": -2028.6, "fwd_capacity": 670.0, "rev_capacity": 2780.0, "fwd_free": 2676.051, "rev_free": 751.4, "fwd_split": "651.353", "rev_split": "分断なし"}, {"time": "10:00", "flow": -1924.3, "fwd_capacity": 650.0, "rev_capacity": 2780.0, "fwd_free": 2454.862, "rev_free": 855.7, "fwd_split": "176.524", "rev_split": "分断なし"}, {"time": "10:30", "flow": -1960.1, "fwd_capacity": 630.0, "rev_capacity": 2780.0, "fwd_free": 2390.551, "rev_free": 819.9, "fwd_split": "0", "rev_split": "分断なし"}, {"time": "11:00", "flow": -2284.9, "fwd_capacity": 610.0, "rev_capacity": 2780.0, "fwd_free": 2654.738, "rev_free": 495.1, "fwd_split": "0", "rev_split": "分断なし"}, {"time": "11:30", "flow": -2456.8, "fwd_capacity": 600.0, "rev_capacity": 2780.0, "fwd_free": 2816.638, "rev_free": 323.2, "fwd_split": "0", "rev_split": "分断なし"}, {"time": "12:00", "flow": -2568.4, "fwd_capacity": 590.0, "rev_capacity": 2780.0, "fwd_free": 2877.026, "rev_free": 211.6, "fwd_split": "0", "rev_split": "分断なし"}, {"time": "12:30", "flow": -2431.2, "fwd_capacity": 580.0, "rev_capacity": 2780.0, "fwd_free": 2653.001, "rev_free": 348.8, "fwd_split": "0", "rev_split": "分断なし"}, {"time": "13:00", "flow": -2028.4, "fwd_capacity": 580.0, "rev_capacity": 2780.0, "fwd_free": 2547.08, "rev_free": 751.6, "fwd_split": "0.438", "rev_split": "分断なし"}, {"time": "13:30", "flow": -1934.3, "fwd_capacity": 590.0, "rev_capacity": 2780.0, "fwd_free": 2085.138, "rev_free": 845.7, "fwd_split": "0", "rev_split": "分断なし"}, {"time": "14:00", "flow": -1961.1, "fwd_capacity": 600.0, "rev_capacity": 2780.0, "fwd_free": 2301.106, "rev_free": 818.9, "fwd_split": "447.326", "rev_split": "分断なし"}, {"time": "14:30", "flow": -2081.3, "fwd_capacity": 610.0, "rev_capacity": 2780.0, "fwd_free": 2528.601, "rev_free": 688.7, "fwd_split": "597.43", "rev_split": "分断なし"}, {"time": "15:00", "flow": -1973.9, "fwd_capacity": 630.0, "rev_capacity": 2780.0, "fwd_free": 2493.875, "rev_free": 796.1, "fwd_split": "1286.353", "rev_split": "分断なし"}, {"time": "15:30", "flow": -1939.3, "fwd_capacity": 710.0, "rev_capacity": 2780.0, "fwd_free": 2482.859, "rev_free": 810.727, "fwd_split": "1490.131", "rev_split": "分断なし"}, {"time": "16:00", "flow": -1868.8, "fwd_capacity": 790.0, "rev_capacity": 2780.0, "fwd_free": 2475.791, "rev_free": 911.2, "fwd_split": "1433.55", "rev_split": "分断なし"}, {"time": "16:30", "flow": -1295.1, "fwd_capacity": 830.0, "rev_capacity": 2780.0, "fwd_free": 1989.401, "rev_free": 1444.9, "fwd_split": "1601.549", "rev_split": "分断なし"}, {"time": "17:00", "flow": -1183.0, "fwd_capacity": 870.0, "rev_capacity": 2780.0, "fwd_free": 1863.487, "rev_free": 1571.51, "fwd_split": "1629.481", "rev_split": "分断なし"}, {"time": "17:30", "flow": -899.0, "fwd_capacity": 910.0, "rev_capacity": 2780.0, "fwd_free": 1753.853, "rev_free": 1791.552, "fwd_split": "1932.129", "rev_split": "分断なし"}, {"time": "18:00", "flow": -776.8, "fwd_capacity": 950.0, "rev_capacity": 2740.0, "fwd_free": 1717.8, "rev_free": 1908.603, "fwd_split": "1892.916", "rev_split": "分断なし"}, {"time": "18:30", "flow": -316.0, "fwd_capacity": 960.0, "rev_capacity": 2710.0, "fwd_free": 940.511, "rev_free": 2394.0, "fwd_split": "2361.08", "rev_split": "分断なし"}, {"time": "19:00", "flow": 59.1, "fwd_capacity": 970.0, "rev_capacity": 2670.0, "fwd_free": 697.034, "rev_free": 2729.1, "fwd_split": "2736.242", "rev_split": "分断なし"}, {"time": "19:30", "flow": -10.6, "fwd_capacity": 980.0, "rev_capacity": 2630.0, "fwd_free": 745.034, "rev_free": 2619.4, "fwd_split": "2710.255", "rev_split": "分断なし"}, {"time": "20:00", "flow": -206.7, "fwd_capacity": 970.0, "rev_capacity": 2570.0, "fwd_free": 877.42, "rev_free": 2363.3, "fwd_split": "2572.224", "rev_split": "分断なし"}, {"time": "20:30", "flow": -371.8, "fwd_capacity": 960.0, "rev_capacity": 2520.0, "fwd_free": 1280.535, "rev_free": 2142.786, "fwd_split": "2540.556", "rev_split": "分断なし"}, {"time": "21:00", "flow": -490.6, "fwd_capacity": 940.0, "rev_capacity": 2470.0, "fwd_free": 1263.882, "rev_free": 1975.486, "fwd_split": "2409.483", "rev_split": "分断なし"}, {"time": "21:30", "flow": -711.3, "fwd_capacity": 930.0, "rev_capacity": 2420.0, "fwd_free": 1460.972, "rev_free": 1699.7, "fwd_split": "2244.84", "rev_split": "分断なし"}, {"time": "22:00", "flow": -746.3, "fwd_capacity": 930.0, "rev_capacity": 2420.0, "fwd_free": 1441.3, "rev_free": 1667.596, "fwd_split": "2243.751", "rev_split": "分断なし"}, {"time": "22:30", "flow": -752.6, "fwd_capacity": 910.0, "rev_capacity": 2330.0, "fwd_free": 1427.6, "rev_free": 1573.28, "fwd_split": "2164.154", "rev_split": "分断なし"}, {"time": "23:00", "flow": -718.2, "fwd_capacity": 900.0, "rev_capacity": 2280.0, "fwd_free": 1384.2, "rev_free": 1555.211, "fwd_split": "2159.105", "rev_split": "分断なし"}, {"time": "23:30", "flow": -1140.2, "fwd_capacity": 890.0, "rev_capacity": 2230.0, "fwd_free": 1812.2, "rev_free": 1079.211, "fwd_split": "1686.064", "rev_split": "分断なし"}, {"time": "24:00", "flow": -889.0, "fwd_capacity": 870.0, "rev_capacity": 2160.0, "fwd_free": 1555.0, "rev_free": 1268.49, "fwd_split": "1920.147", "rev_split": "分断なし"}]}}